results/issue-3/code/spi_dual_mode2_32bit.v
// =============================================
// SPI Dual Mode Core - Auto-generated by SPI Customizer
// Supports both Master and Slave functionality
// =============================================

module spi_dual #(
    parameter MODE = 2,                    // SPI mode (0, 1, 2, 3)
    parameter DATA_WIDTH = 32,        // Data width in bits
    parameter NUM_SLAVES = 4,        // Number of slaves when in master mode
    parameter SLAVE_ACTIVE_LOW = 1,  // Slave select polarity
    parameter MSB_FIRST = 1,  // Data order
    parameter FIFO_DEPTH = 16,        // FIFO buffer depth
    parameter MAX_SLAVES = 8,        // Maximum slaves supported
    parameter CLOCK_DIVIDER = 2,  // System clock divider
    parameter DEFAULT_DATA_ENABLED = 0,
    parameter DEFAULT_DATA_VALUE = 32'hA5A5A5A5
)(
    // System signals
    input  wire clk,                    // System clock
    input  wire rst_n,                  // Active-low reset

    // Mode selection
    input  wire master_mode,            // 1 = Master, 0 = Slave

    // Master Interface (when master_mode = 1)
    output wire sclk,                   // SPI clock output
    output wire mosi,                   // Master Out Slave In
    input  wire miso,                   // Master In Slave Out
    output wire [NUM_SLAVES-1:0] ss_n,  // Slave Select outputs

    // Slave Interface (when master_mode = 0)
    input  wire sclk_in,                // SPI clock input
    input  wire mosi_in,                // MOSI input
    output wire miso_out,               // MISO output
    input  wire ss_in,                  // Slave Select input

    // Common Data Interface
    output wire [DATA_WIDTH-1:0] rx_data,  // Received data
    input  wire [DATA_WIDTH-1:0] tx_data,  // Data to transmit
    output wire rx_valid,               // Receive data valid
    output wire tx_ready,               // Ready to accept new transmit data
    input  wire tx_valid,               // Transmit data valid

    // Control and status
    output wire busy,                   // SPI transaction in progress
    output wire irq,                    // Interrupt request
    input  wire irq_clear               // Clear interrupt
);

    // Internal signals
    localparam SLAVE_TIMEOUT_CYCLES = 8'd200; // Timeout after ~200 system clock cycles
    localparam CPOL = (MODE == 2 || MODE == 3) ? 1 : 0; // Clock polarity: 1=idles high
    localparam SAMPLE_ON_RISING = (MODE == 0 || MODE == 3) ? 1 : 0; // 1=sample rising, 0=sample falling
    reg [DATA_WIDTH-1:0] default_data;

    // Master mode internal signals
    reg master_start_tx, master_start_rx;
    reg [DATA_WIDTH-1:0] master_tx_shift_reg, master_rx_shift_reg;
    reg [7:0] master_bit_counter;
    reg [7:0] master_sclk_counter;
    reg master_busy, master_sclk_en;
    reg [NUM_SLAVES-1:0] master_ss_n_reg;
    reg [DATA_WIDTH-1:0] master_rx_data_buffer;
    reg master_rx_valid_buffer, master_tx_ready_buffer;

    // Slave mode internal signals
    reg slave_rx_valid_buffer, slave_tx_ready_buffer, slave_busy_buffer;
    reg [DATA_WIDTH-1:0] slave_rx_data_buffer;
    reg [DATA_WIDTH-1:0] slave_tx_shift_reg;
    reg [7:0] slave_bit_counter;
    reg slave_sclk_last_state, slave_ss_last_state;
    reg slave_transaction_active;
    reg [7:0] slave_timeout_counter;

    // Default data initialization
    initial begin
        default_data <= DEFAULT_DATA_VALUE;
    end

    // Master mode implementation
    always @(posedge clk or negedge rst_n) begin
        if (!rst_n) begin
            master_busy <= 1'b0;
            master_sclk_en <= 1'b0;
            master_start_tx <= 1'b0;
            master_start_rx <= 1'b0;
            master_tx_ready_buffer <= 1'b1; // Ready to accept data initially
            master_rx_valid_buffer <= 1'b0;
            master_bit_counter <= 8'd0;
            master_sclk_counter <= 8'd0;
            master_tx_shift_reg <= {DATA_WIDTH{1'b0}};
            master_rx_shift_reg <= {DATA_WIDTH{1'b0}};
            master_ss_n_reg <= {NUM_SLAVES{1'b1}}; // Deasserted (active low)
        end else if (master_mode) begin
            // Master mode logic
            if (tx_valid && master_tx_ready_buffer && !master_busy) begin
                // Start new transmission
                master_tx_shift_reg <= tx_data;
                master_tx_ready_buffer <= 1'b0; // Not ready during transmission
                master_busy <= 1'b1;
                master_sclk_en <= 1'b1;
                master_bit_counter <= 8'd0;
                master_sclk_counter <= 8'd0;
                master_start_tx <= 1'b1;
                // Assert slave 0 (active low): all bits high except bit 0
                master_ss_n_reg <= {NUM_SLAVES{1'b1}};
                master_ss_n_reg[0] <= 1'b0;
            end else begin
                master_start_tx <= 1'b0;
            end

            // SPI clock generation and data shifting
            if (master_busy && master_sclk_en) begin
                master_sclk_counter <= master_sclk_counter + 1'b1;

                // Generate SPI clock (divide by CLOCK_DIVIDER)
                if (master_sclk_counter >= CLOCK_DIVIDER) begin
                    master_sclk_counter <= 8'd0;

                    // SPI Mode 0: Sample on rising edge, change on falling edge
                    // For simplicity, we'll toggle and sample on each clock edge
                    if (master_bit_counter < DATA_WIDTH) begin
                        // Shift data
                        if (MSB_FIRST) begin
                            if (DATA_WIDTH > 1) begin
                                master_tx_shift_reg <= {master_tx_shift_reg[DATA_WIDTH-2:0], 1'b0};
                            end else begin
                                master_tx_shift_reg <= 1'b0;  // For 1-bit, just set to 0 after transmission
                            end
                        end else begin
                            if (DATA_WIDTH > 1) begin
                                master_tx_shift_reg <= {1'b0, master_tx_shift_reg[DATA_WIDTH-1:1]};
                            end else begin
                                master_tx_shift_reg <= 1'b0;  // For 1-bit, just set to 0 after transmission
                            end
                        end
                        master_bit_counter <= master_bit_counter + 1'b1;
                    end else begin
                        // Transmission complete
                        master_busy <= 1'b0;
                        master_sclk_en <= 1'b0;
                        master_tx_ready_buffer <= 1'b1; // Ready for next transmission
                        master_rx_valid_buffer <= 1'b1; // Data received
                        master_rx_data_buffer <= master_rx_shift_reg;
                        master_ss_n_reg <= {NUM_SLAVES{1'b1}}; // Deassert slave select
                    end
                end
            end
        end
    end

    // Slave mode implementation - proper SPI protocol handling
    always @(posedge clk or negedge rst_n) begin
        if (!rst_n) begin
            slave_busy_buffer <= 1'b0;
            slave_rx_valid_buffer <= 1'b0;
            slave_tx_ready_buffer <= 1'b0;
            slave_rx_data_buffer <= {DATA_WIDTH{1'b0}};
            slave_tx_shift_reg <= default_data;
            slave_bit_counter <= 8'd0;
            slave_sclk_last_state <= CPOL[0]; // Initialize to CPOL idle state
            slave_ss_last_state <= 1'b1;
            slave_transaction_active <= 1'b0;
            slave_timeout_counter <= 8'd0;
        end else if (!master_mode) begin
            // Detect SS transitions
            slave_ss_last_state <= ss_in;

            // Start transaction on SS falling edge
            if (slave_ss_last_state && !ss_in) begin
                slave_transaction_active <= 1'b1;
                slave_busy_buffer <= 1'b1;
                slave_bit_counter <= 8'd0;
                slave_tx_shift_reg <= tx_data; // Load data to transmit
                slave_tx_ready_buffer <= 1'b0; // Not ready for new data during transaction
            end

            // End transaction on SS rising edge
            if (!slave_ss_last_state && ss_in && slave_transaction_active) begin
                slave_transaction_active <= 1'b0;
                slave_busy_buffer <= 1'b0;
                slave_rx_valid_buffer <= 1'b1; // Data received
                slave_tx_ready_buffer <= 1'b1; // Ready for new transmit data
            end

            // Handle SPI clock edges during active transaction
            if (slave_transaction_active) begin
                slave_sclk_last_state <= sclk_in;
                slave_timeout_counter <= slave_timeout_counter + 1'b1;

                // Timeout mechanism - force completion after ~200 clock cycles
                if (slave_timeout_counter > SLAVE_TIMEOUT_CYCLES) begin
                    slave_transaction_active <= 1'b0;
                    slave_busy_buffer <= 1'b0;
                    slave_rx_valid_buffer <= 1'b1; // Data received (partial)
                    slave_tx_ready_buffer <= 1'b1; // Ready for new transmit data
                    slave_timeout_counter <= 8'd0;
                end else begin
                    // Sample on the correct edge based on SPI mode
                    // SAMPLE_ON_RISING=1 for modes 0,3; =0 for modes 1,2
                    if (SAMPLE_ON_RISING ? (!slave_sclk_last_state && sclk_in) : (slave_sclk_last_state && !sclk_in)) begin
                    // Sample MOSI data
                    if (MSB_FIRST) begin
                        if (DATA_WIDTH > 1) begin
                            slave_rx_data_buffer <= {slave_rx_data_buffer[DATA_WIDTH-2:0], mosi_in};
                        end else begin
                            slave_rx_data_buffer <= mosi_in;  // For 1-bit, just set to received bit
                        end
                    end else begin
                        if (DATA_WIDTH > 1) begin
                            slave_rx_data_buffer <= {mosi_in, slave_rx_data_buffer[DATA_WIDTH-1:1]};
                        end else begin
                            slave_rx_data_buffer <= mosi_in;  // For 1-bit, just set to received bit
                        end
                    end
                        slave_bit_counter <= slave_bit_counter + 1'b1;

                        // Auto-complete transaction after all bits received
                        if (slave_bit_counter >= DATA_WIDTH) begin
                            slave_transaction_active <= 1'b0;
                            slave_busy_buffer <= 1'b0;
                            slave_rx_valid_buffer <= 1'b1; // Data received
                            slave_tx_ready_buffer <= 1'b1; // Ready for new transmit data
                            slave_timeout_counter <= 8'd0;
                        end
                    end
                end
                // Note: MISO changes on falling edge would be handled here if needed
            end else begin
                // Not in transaction
                slave_rx_valid_buffer <= 1'b0;
                slave_tx_ready_buffer <= 1'b1;
                slave_timeout_counter <= 8'd0;
            end
        end
    end

    // Output signal selection based on master_mode
    // SCLK idles at CPOL level; XOR with CPOL inverts the counter parity for correct polarity
    assign sclk = master_mode ? (master_sclk_en ? (master_sclk_counter[0] ^ (CPOL ? 1'b1 : 1'b0)) : (CPOL ? 1'b1 : 1'b0)) : 1'b0;
    assign mosi = master_mode ? master_tx_shift_reg[MSB_FIRST ? DATA_WIDTH-1 : 0] : 1'b0;
    assign miso_out = master_mode ? 1'b0 : (slave_tx_ready_buffer ? default_data[MSB_FIRST ? DATA_WIDTH-1 : 0] : 1'b0);

    // Slave select outputs: active-low, slave 0 asserted during master transmission
    assign ss_n = master_mode ? master_ss_n_reg : {NUM_SLAVES{1'b1}};

    // Data signal selection
    assign rx_data = master_mode ? master_rx_data_buffer : slave_rx_data_buffer;
    assign rx_valid = master_mode ? master_rx_valid_buffer : slave_rx_valid_buffer;
    assign tx_ready = master_mode ? master_tx_ready_buffer : slave_tx_ready_buffer;
    assign busy = master_mode ? master_busy : slave_busy_buffer;

    // Simplified output assignments
    assign irq = 1'b0;  // No interrupts for now

endmodule

results/issue-3/code/spi_dual_tb.v
// =============================================
// SPI Dual Mode Testbench - Auto-generated by SPI Customizer
// =============================================

`timescale 1ns / 1ps

module spi_dual_tb;

    // Parameters
    parameter MODE = 2;
    parameter DATA_WIDTH = 32;
    parameter NUM_SLAVES = 4;
    parameter SLAVE_ACTIVE_LOW = 1;
    parameter MSB_FIRST = 1;
    parameter FIFO_DEPTH = 16;
    parameter MAX_SLAVES = 8;
    parameter CLOCK_DIVIDER = 2;
    parameter DEFAULT_DATA_ENABLED = 0;
    parameter DEFAULT_DATA_VALUE = 32'hA5A5A5A5;
    localparam integer SLAVE_TEST_BITS = (DATA_WIDTH < 8) ? DATA_WIDTH : 8;
    localparam [7:0] SLAVE_TEST_BYTE = 8'h5A;

    // Signals
    reg clk;
    reg rst_n;
    reg master_mode;
    wire sclk;
    wire mosi;
    reg miso;
    wire [NUM_SLAVES-1:0] ss_n;
    reg sclk_in;
    reg mosi_in;
    wire miso_out;
    reg ss_in;
    reg [DATA_WIDTH-1:0] tx_data;
    wire [DATA_WIDTH-1:0] rx_data;
    wire rx_valid;
    wire tx_ready;
    reg tx_valid;
    wire busy;
    wire irq;
    integer i;
    reg [DATA_WIDTH-1:0] expected_slave_rx;
    reg [DATA_WIDTH-1:0] captured_slave_bits;
    reg [7:0] timeout_cycles;
    reg slave_rx_valid_seen;

    // DUT instantiation
    spi_dual #(
        .MODE(MODE),
        .DATA_WIDTH(DATA_WIDTH),
        .NUM_SLAVES(NUM_SLAVES),
        .SLAVE_ACTIVE_LOW(SLAVE_ACTIVE_LOW),
        .MSB_FIRST(MSB_FIRST),
        .FIFO_DEPTH(FIFO_DEPTH),
        .MAX_SLAVES(MAX_SLAVES),
        .CLOCK_DIVIDER(CLOCK_DIVIDER),
        .DEFAULT_DATA_ENABLED(DEFAULT_DATA_ENABLED),
        .DEFAULT_DATA_VALUE(DEFAULT_DATA_VALUE)
    ) dut (
        .clk(clk),
        .rst_n(rst_n),
        .master_mode(master_mode),
        .sclk(sclk),
        .mosi(mosi),
        .miso(miso),
        .ss_n(ss_n),
        .sclk_in(sclk_in),
        .mosi_in(mosi_in),
        .miso_out(miso_out),
        .ss_in(ss_in),
        .rx_data(rx_data),
        .tx_data(tx_data),
        .rx_valid(rx_valid),
        .tx_ready(tx_ready),
        .tx_valid(tx_valid),
        .busy(busy),
        .irq(irq),
        .irq_clear(1'b0)
    );

    // Clock generation
    initial begin
        clk = 0;
        forever #10 clk = ~clk;  // 50MHz clock
    end

    // Test sequence for dual mode
    initial begin
        // Initialize
        rst_n = 0;
        master_mode = 1;  // Start in master mode
        tx_data = 0;
        tx_valid = 0;
        miso = 0;
        sclk_in = (MODE == 2 || MODE == 3) ? 1 : 0; // CPOL idle state
        mosi_in = 0;
        ss_in = 1;
        slave_rx_valid_seen = 0;

        #100;
        rst_n = 1;
        #200;  // Allow system to stabilize

        $display("=== SPI Dual Mode RTL Testbench Starting ===");
        $display("Configuration: Mode %d, %d-bit data, Dual mode", MODE, DATA_WIDTH);

        // Test master mode first
        $display("--- Testing Master Mode ---");

        // Test basic transmission in master mode
        tx_data = 32'hA5A5A5A5;
        $display("TX Data: 0x%h", tx_data);

        // Wait for tx_ready to be asserted (may already be high)
        wait(tx_ready);
        #10; // Small delay
        tx_valid = 1; // Assert tx_valid to start transmission
        #20; // Hold tx_valid for a few cycles
        tx_valid = 0; // Deassert tx_valid

        // Wait for transmission to complete (with timeout)
        begin : wait_master
            localparam MASTER_TX_TIMEOUT_CYCLES = 5000;
            integer timeout;
            timeout = 0;
            while (!tx_ready && timeout < MASTER_TX_TIMEOUT_CYCLES) begin
                #20;
                timeout = timeout + 1;
            end
            if (timeout >= MASTER_TX_TIMEOUT_CYCLES)
                $display("WARNING: Master transmission timeout");
            else
                $display("Master transmission complete");
        end

        // Switch to slave mode after master test
        #500;
        master_mode = 0;
        $display("--- Switched to Slave Mode ---");

        // Test slave mode with proper SPI master simulation
        #100;

        // Simulate a complete SPI transaction as master to our slave
        $display("Simulating SPI master transaction to test slave mode");

        // Start transaction: assert SS low
        ss_in = 0;
        $display("Slave selected (SS asserted low)");

        // SPI Mode 2: CPOL=1, CPHA=0
        // Sampling occurs on falling edge
        // Send SLAVE_TEST_BITS bits from SLAVE_TEST_BYTE (MSB first over tested window)
        expected_slave_rx = {DATA_WIDTH{1'b0}};
        captured_slave_bits = {DATA_WIDTH{1'b0}};

        for (i = 0; i < SLAVE_TEST_BITS; i = i + 1) begin
            mosi_in = SLAVE_TEST_BYTE[SLAVE_TEST_BITS - 1 - i];
            captured_slave_bits = {captured_slave_bits[DATA_WIDTH-2:0], mosi_in};
            #50;
            sclk_in = 0; // Leading edge
            #50;
            sclk_in = 1; // Trailing edge
        end

        expected_slave_rx = captured_slave_bits;

        // Return clock to idle
        sclk_in = (MODE == 2 || MODE == 3) ? 1 : 0;

        // End transaction: deassert SS
        #100;
        ss_in = 1;
        $display("Slave mode SPI transaction complete - sent 0x%0h (%0d bits)", SLAVE_TEST_BYTE, SLAVE_TEST_BITS);

        #200; // Allow slave to process

        // Wait for slave rx_valid pulse with timeout, then check payload
        timeout_cycles = 0;
        while (!slave_rx_valid_seen && timeout_cycles < 100) begin
            #20;
            timeout_cycles = timeout_cycles + 1;
        end
        if (!slave_rx_valid_seen) begin
            $fatal(1, "Slave rx_valid did not assert within timeout");
        end

        if (rx_data !== expected_slave_rx) begin
            $fatal(1, "Slave RX mismatch. expected=0x%h got=0x%h", expected_slave_rx, rx_data);
        end else begin
            $display("Slave RX matched expected payload: 0x%h", rx_data);
        end

        $display("=== All Dual Mode Tests Completed Successfully ===");
        #100; // Small delay before finish
        $finish;
    end

    // Latch rx_valid pulse so the check is robust to single-cycle assertions
    always @(posedge clk or negedge rst_n) begin
        if (!rst_n)
            slave_rx_valid_seen <= 1'b0;
        else if (rx_valid)
            slave_rx_valid_seen <= 1'b1;
    end

    // VCD dumping
    initial begin
        $dumpfile("results/issue-3/data/spi_waveform.vcd");
        $dumpvars(0, spi_dual_tb);
    end

endmodule

results/issue-3/data/spi_waveform.vcd
$date
	Mon Apr 27 01:16:36 2026
$end
$version
	Icarus Verilog
$end
$timescale
	1ps
$end
$scope module spi_dual_tb $end
$var wire 1 ! irq $end
$var wire 1 " tx_ready $end
$var wire 4 # ss_n [3:0] $end
$var wire 1 $ sclk $end
$var wire 1 % rx_valid $end
$var wire 32 & rx_data [31:0] $end
$var wire 1 ' mosi $end
$var wire 1 ( miso_out $end
$var wire 1 ) busy $end
$var parameter 32 * CLOCK_DIVIDER $end
$var parameter 32 + DATA_WIDTH $end
$var parameter 32 , DEFAULT_DATA_ENABLED $end
$var parameter 32 - DEFAULT_DATA_VALUE $end
$var parameter 32 . FIFO_DEPTH $end
$var parameter 32 / MAX_SLAVES $end
$var parameter 32 0 MODE $end
$var parameter 32 1 MSB_FIRST $end
$var parameter 32 2 NUM_SLAVES $end
$var parameter 32 3 SLAVE_ACTIVE_LOW $end
$var parameter 32 4 SLAVE_TEST_BITS $end
$var parameter 8 5 SLAVE_TEST_BYTE $end
$var reg 32 6 captured_slave_bits [31:0] $end
$var reg 1 7 clk $end
$var reg 32 8 expected_slave_rx [31:0] $end
$var reg 1 9 master_mode $end
$var reg 1 : miso $end
$var reg 1 ; mosi_in $end
$var reg 1 < rst_n $end
$var reg 1 = sclk_in $end
$var reg 1 > slave_rx_valid_seen $end
$var reg 1 ? ss_in $end
$var reg 8 @ timeout_cycles [7:0] $end
$var reg 32 A tx_data [31:0] $end
$var reg 1 B tx_valid $end
$var integer 32 C i [31:0] $end
$scope module dut $end
$var wire 1 7 clk $end
$var wire 1 ! irq $end
$var wire 1 D irq_clear $end
$var wire 1 9 master_mode $end
$var wire 1 : miso $end
$var wire 1 ; mosi_in $end
$var wire 1 < rst_n $end
$var wire 1 = sclk_in $end
$var wire 1 ? ss_in $end
$var wire 32 E tx_data [31:0] $end
$var wire 1 B tx_valid $end
$var wire 1 " tx_ready $end
$var wire 4 F ss_n [3:0] $end
$var wire 1 $ sclk $end
$var wire 1 % rx_valid $end
$var wire 32 G rx_data [31:0] $end
$var wire 1 ' mosi $end
$var wire 1 ( miso_out $end
$var wire 1 ) busy $end
$var parameter 32 H CLOCK_DIVIDER $end
$var parameter 32 I CPOL $end
$var parameter 32 J DATA_WIDTH $end
$var parameter 32 K DEFAULT_DATA_ENABLED $end
$var parameter 32 L DEFAULT_DATA_VALUE $end
$var parameter 32 M FIFO_DEPTH $end
$var parameter 32 N MAX_SLAVES $end
$var parameter 32 O MODE $end
$var parameter 32 P MSB_FIRST $end
$var parameter 32 Q NUM_SLAVES $end
$var parameter 32 R SAMPLE_ON_RISING $end
$var parameter 32 S SLAVE_ACTIVE_LOW $end
$var parameter 8 T SLAVE_TIMEOUT_CYCLES $end
$var reg 32 U default_data [31:0] $end
$var reg 8 V master_bit_counter [7:0] $end
$var reg 1 W master_busy $end
$var reg 32 X master_rx_data_buffer [31:0] $end
$var reg 32 Y master_rx_shift_reg [31:0] $end
$var reg 1 Z master_rx_valid_buffer $end
$var reg 8 [ master_sclk_counter [7:0] $end
$var reg 1 \ master_sclk_en $end
$var reg 4 ] master_ss_n_reg [3:0] $end
$var reg 1 ^ master_start_rx $end
$var reg 1 _ master_start_tx $end
$var reg 1 ` master_tx_ready_buffer $end
$var reg 32 a master_tx_shift_reg [31:0] $end
$var reg 8 b slave_bit_counter [7:0] $end
$var reg 1 c slave_busy_buffer $end
$var reg 32 d slave_rx_data_buffer [31:0] $end
$var reg 1 e slave_rx_valid_buffer $end
$var reg 1 f slave_sclk_last_state $end
$var reg 1 g slave_ss_last_state $end
$var reg 8 h slave_timeout_counter [7:0] $end
$var reg 1 i slave_transaction_active $end
$var reg 1 j slave_tx_ready_buffer $end
$var reg 32 k slave_tx_shift_reg [31:0] $end
$upscope $end
$scope begin wait_master $end
$var parameter 32 l MASTER_TX_TIMEOUT_CYCLES $end
$var integer 32 m timeout [31:0] $end
$upscope $end
$upscope $end
$enddefinitions $end
$comment Show the parameter values. $end
$dumpall
b1001110001000 l
b11001000 T
b1 S
b0 R
b100 Q
b1 P
b10 O
b1000 N
b10000 M
b10100101101001011010010110100101 L
b0 K
b100000 J
b1 I
b10 H
b1011010 5
b1000 4
b1 3
b100 2
b1 1
b10 0
b1000 /
b10000 .
b10100101101001011010010110100101 -
b0 ,
b100000 +
b10 *
$end
#0
$dumpvars
bx m
bx k
0j
0i
b0 h
1g
1f
0e
b0 d
0c
b0 b
b0 a
1`
0_
0^
b1111 ]
0\
b0 [
0Z
b0 Y
bx X
0W
b0 V
b10100101101001011010010110100101 U
bx G
b1111 F
b0 E
0D
bx C
0B
b0 A
bx @
1?
0>
1=
0<
0;
0:
19
bx 8
07
bx 6
0)
0(
0'
bx &
0%
1$
b1111 #
1"
0!
$end
#10000
b10100101101001011010010110100101 k
17
#20000
07
#30000
17
#40000
07
#50000
17
#60000
07
#70000
17
#80000
07
#90000
17
#100000
07
1<
#110000
17
#120000
07
#130000
17
#140000
07
#150000
17
#160000
07
#170000
17
#180000
07
#190000
17
#200000
07
#210000
17
#220000
07
#230000
17
#240000
07
#250000
17
#260000
07
#270000
17
#280000
07
#290000
17
#300000
07
b10100101101001011010010110100101 A
b10100101101001011010010110100101 E
#310000
1'
b1110 #
b1110 F
1)
0"
b1110 ]
1_
1\
1W
0`
b10100101101001011010010110100101 a
17
1B
#320000
07
#330000
0$
b1 [
0_
17
b0 m
0B
#340000
07
#350000
1$
b10 [
17
b1 m
#360000
07
#370000
0'
b1 V
b1001011010010110100101101001010 a
b0 [
17
b10 m
#380000
07
#390000
0$
b1 [
17
b11 m
#400000
07
#410000
1$
b10 [
17
b100 m
#420000
07
#430000
1'
b10 V
b10010110100101101001011010010100 a
b0 [
17
b101 m
#440000
07
#450000
0$
b1 [
17
b110 m
#460000
07
#470000
1$
b10 [
17
b111 m
#480000
07
#490000
0'
b11 V
b101101001011010010110100101000 a
b0 [
17
b1000 m
#500000
07
#510000
0$
b1 [
17
b1001 m
#520000
07
#530000
1$
b10 [
17
b1010 m
#540000
07
#550000
b100 V
b1011010010110100101101001010000 a
b0 [
17
b1011 m
#560000
07
#570000
0$
b1 [
17
b1100 m
#580000
07
#590000
1$
b10 [
17
b1101 m
#600000
07
#610000
1'
b101 V
b10110100101101001011010010100000 a
b0 [
17
b1110 m
#620000
07
#630000
0$
b1 [
17
b1111 m
#640000
07
#650000
1$
b10 [
17
b10000 m
#660000
07
#670000
0'
b110 V
b1101001011010010110100101000000 a
b0 [
17
b10001 m
#680000
07
#690000
0$
b1 [
17
b10010 m
#700000
07
#710000
1$
b10 [
17
b10011 m
#720000
07
#730000
1'
b111 V
b11010010110100101101001010000000 a
b0 [
17
b10100 m
#740000
07
#750000
0$
b1 [
17
b10101 m
#760000
07
#770000
1$
b10 [
17
b10110 m
#780000
07
#790000
b1000 V
b10100101101001011010010100000000 a
b0 [
17
b10111 m
#800000
07
#810000
0$
b1 [
17
b11000 m
#820000
07
#830000
1$
b10 [
17
b11001 m
#840000
07
#850000
0'
b1001 V
b1001011010010110100101000000000 a
b0 [
17
b11010 m
#860000
07
#870000
0$
b1 [
17
b11011 m
#880000
07
#890000
1$
b10 [
17
b11100 m
#900000
07
#910000
1'
b1010 V
b10010110100101101001010000000000 a
b0 [
17
b11101 m
#920000
07
#930000
0$
b1 [
17
b11110 m
#940000
07
#950000
1$
b10 [
17
b11111 m
#960000
07
#970000
0'
b1011 V
b101101001011010010100000000000 a
b0 [
17
b100000 m
#980000
07
#990000
0$
b1 [
17
b100001 m
#1000000
07
#1010000
1$
b10 [
17
b100010 m
#1020000
07
#1030000
b1100 V
b1011010010110100101000000000000 a
b0 [
17
b100011 m
#1040000
07
#1050000
0$
b1 [
17
b100100 m
#1060000
07
#1070000
1$
b10 [
17
b100101 m
#1080000
07
#1090000
1'
b1101 V
b10110100101101001010000000000000 a
b0 [
17
b100110 m
#1100000
07
#1110000
0$
b1 [
17
b100111 m
#1120000
07
#1130000
1$
b10 [
17
b101000 m
#1140000
07
#1150000
0'
b1110 V
b1101001011010010100000000000000 a
b0 [
17
b101001 m
#1160000
07
#1170000
0$
b1 [
17
b101010 m
#1180000
07
#1190000
1$
b10 [
17
b101011 m
#1200000
07
#1210000
1'
b1111 V
b11010010110100101000000000000000 a
b0 [
17
b101100 m
#1220000
07
#1230000
0$
b1 [
17
b101101 m
#1240000
07
#1250000
1$
b10 [
17
b101110 m
#1260000
07
#1270000
b10000 V
b10100101101001010000000000000000 a
b0 [
17
b101111 m
#1280000
07
#1290000
0$
b1 [
17
b110000 m
#1300000
07
#1310000
1$
b10 [
17
b110001 m
#1320000
07
#1330000
0'
b10001 V
b1001011010010100000000000000000 a
b0 [
17
b110010 m
#1340000
07
#1350000
0$
b1 [
17
b110011 m
#1360000
07
#1370000
1$
b10 [
17
b110100 m
#1380000
07
#1390000
1'
b10010 V
b10010110100101000000000000000000 a
b0 [
17
b110101 m
#1400000
07
#1410000
0$
b1 [
17
b110110 m
#1420000
07
#1430000
1$
b10 [
17
b110111 m
#1440000
07
#1450000
0'
b10011 V
b101101001010000000000000000000 a
b0 [
17
b111000 m
#1460000
07
#1470000
0$
b1 [
17
b111001 m
#1480000
07
#1490000
1$
b10 [
17
b111010 m
#1500000
07
#1510000
b10100 V
b1011010010100000000000000000000 a
b0 [
17
b111011 m
#1520000
07
#1530000
0$
b1 [
17
b111100 m
#1540000
07
#1550000
1$
b10 [
17
b111101 m
#1560000
07
#1570000
1'
b10101 V
b10110100101000000000000000000000 a
b0 [
17
b111110 m
#1580000
07
#1590000
0$
b1 [
17
b111111 m
#1600000
07
#1610000
1$
b10 [
17
b1000000 m
#1620000
07
#1630000
0'
b10110 V
b1101001010000000000000000000000 a
b0 [
17
b1000001 m
#1640000
07
#1650000
0$
b1 [
17
b1000010 m
#1660000
07
#1670000
1$
b10 [
17
b1000011 m
#1680000
07
#1690000
1'
b10111 V
b11010010100000000000000000000000 a
b0 [
17
b1000100 m
#1700000
07
#1710000
0$
b1 [
17
b1000101 m
#1720000
07
#1730000
1$
b10 [
17
b1000110 m
#1740000
07
#1750000
b11000 V
b10100101000000000000000000000000 a
b0 [
17
b1000111 m
#1760000
07
#1770000
0$
b1 [
17
b1001000 m
#1780000
07
#1790000
1$
b10 [
17
b1001001 m
#1800000
07
#1810000
0'
b11001 V
b1001010000000000000000000000000 a
b0 [
17
b1001010 m
#1820000
07
#1830000
0$
b1 [
17
b1001011 m
#1840000
07
#1850000
1$
b10 [
17
b1001100 m
#1860000
07
#1870000
1'
b11010 V
b10010100000000000000000000000000 a
b0 [
17
b1001101 m
#1880000
07
#1890000
0$
b1 [
17
b1001110 m
#1900000
07
#1910000
1$
b10 [
17
b1001111 m
#1920000
07
#1930000
0'
b11011 V
b101000000000000000000000000000 a
b0 [
17
b1010000 m
#1940000
07
#1950000
0$
b1 [
17
b1010001 m
#1960000
07
#1970000
1$
b10 [
17
b1010010 m
#1980000
07
#1990000
b11100 V
b1010000000000000000000000000000 a
b0 [
17
b1010011 m
#2000000
07
#2010000
0$
b1 [
17
b1010100 m
#2020000
07
#2030000
1$
b10 [
17
b1010101 m
#2040000
07
#2050000
1'
b11101 V
b10100000000000000000000000000000 a
b0 [
17
b1010110 m
#2060000
07
#2070000
0$
b1 [
17
b1010111 m
#2080000
07
#2090000
1$
b10 [
17
b1011000 m
#2100000
07
#2110000
0'
b11110 V
b1000000000000000000000000000000 a
b0 [
17
b1011001 m
#2120000
07
#2130000
0$
b1 [
17
b1011010 m
#2140000
07
#2150000
1$
b10 [
17
b1011011 m
#2160000
07
#2170000
1'
b11111 V
b10000000000000000000000000000000 a
b0 [
17
b1011100 m
#2180000
07
#2190000
0$
b1 [
17
b1011101 m
#2200000
07
#2210000
1$
b10 [
17
b1011110 m
#2220000
07
#2230000
0'
b100000 V
b0 a
b0 [
17
b1011111 m
#2240000
07
#2250000
0$
b1 [
17
b1100000 m
#2260000
07
#2270000
1$
b10 [
17
b1100001 m
#2280000
07
#2290000
b1111 #
b1111 F
b0 &
b0 G
1%
1"
0)
b1111 ]
b0 X
1Z
1`
0\
0W
b0 [
17
b1100010 m
#2300000
07
#2310000
1>
17
b1100011 m
