results/issue-3/code/spi_dual_mode2_32bit.v
// =============================================
// SPI Dual Mode Core - Auto-generated by SPI Customizer
// Supports both Master and Slave functionality
// =============================================

module spi_dual #(
    parameter MODE = 2,                    // SPI mode (0, 1, 2, 3)
    parameter DATA_WIDTH = 32,        // Data width in bits
    parameter NUM_SLAVES = 4,        // Number of slaves when in master mode
    parameter SLAVE_ACTIVE_LOW = 1,  // Slave select polarity
    parameter MSB_FIRST = 1,  // Data order
    parameter FIFO_DEPTH = 16,        // FIFO buffer depth
    parameter MAX_SLAVES = 8,        // Maximum slaves supported
    parameter CLOCK_DIVIDER = 2,  // System clock divider
    parameter DEFAULT_DATA_ENABLED = 0,
    parameter DEFAULT_DATA_VALUE = 32'hA5A5A5A5
)(
    // System signals
    input  wire clk,                    // System clock
    input  wire rst_n,                  // Active-low reset

    // Mode selection
    input  wire master_mode,            // 1 = Master, 0 = Slave

    // Master Interface (when master_mode = 1)
    output wire sclk,                   // SPI clock output
    output wire mosi,                   // Master Out Slave In
    input  wire miso,                   // Master In Slave Out
    output wire [NUM_SLAVES-1:0] ss_n,  // Slave Select outputs

    // Slave Interface (when master_mode = 0)
    input  wire sclk_in,                // SPI clock input
    input  wire mosi_in,                // MOSI input
    output wire miso_out,               // MISO output
    input  wire ss_in,                  // Slave Select input

    // Common Data Interface
    output wire [DATA_WIDTH-1:0] rx_data,  // Received data
    input  wire [DATA_WIDTH-1:0] tx_data,  // Data to transmit
    output wire rx_valid,               // Receive data valid
    output wire tx_ready,               // Ready to accept new transmit data
    input  wire tx_valid,               // Transmit data valid

    // Control and status
    output wire busy,                   // SPI transaction in progress
    output wire irq,                    // Interrupt request
    input  wire irq_clear               // Clear interrupt
);

    // Internal signals
    localparam SLAVE_TIMEOUT_CYCLES = 8'd200; // Timeout after ~200 system clock cycles
    localparam CPOL = (MODE == 2 || MODE == 3) ? 1 : 0; // Clock polarity: 1=idles high
    localparam SAMPLE_ON_RISING = (MODE == 0 || MODE == 3) ? 1 : 0; // 1=sample rising, 0=sample falling
    reg [DATA_WIDTH-1:0] default_data;

    // Master mode internal signals
    reg master_start_tx, master_start_rx;
    reg [DATA_WIDTH-1:0] master_tx_shift_reg, master_rx_shift_reg;
    reg [7:0] master_bit_counter;
    reg [7:0] master_sclk_counter;
    reg master_busy, master_sclk_en;
    reg [NUM_SLAVES-1:0] master_ss_n_reg;
    reg [DATA_WIDTH-1:0] master_rx_data_buffer;
    reg master_rx_valid_buffer, master_tx_ready_buffer;

    // Slave mode internal signals
    reg slave_rx_valid_buffer, slave_tx_ready_buffer, slave_busy_buffer;
    reg [DATA_WIDTH-1:0] slave_rx_data_buffer;
    reg [DATA_WIDTH-1:0] slave_tx_shift_reg;
    reg [7:0] slave_bit_counter;
    reg slave_sclk_last_state, slave_ss_last_state;
    reg slave_transaction_active;
    reg [7:0] slave_timeout_counter;

    // Default data initialization
    initial begin
        default_data <= DEFAULT_DATA_VALUE;
    end

    // Master mode implementation
    always @(posedge clk or negedge rst_n) begin
        if (!rst_n) begin
            master_busy <= 1'b0;
            master_sclk_en <= 1'b0;
            master_start_tx <= 1'b0;
            master_start_rx <= 1'b0;
            master_tx_ready_buffer <= 1'b1; // Ready to accept data initially
            master_rx_valid_buffer <= 1'b0;
            master_bit_counter <= 8'd0;
            master_sclk_counter <= 8'd0;
            master_tx_shift_reg <= {DATA_WIDTH{1'b0}};
            master_rx_shift_reg <= {DATA_WIDTH{1'b0}};
            master_ss_n_reg <= {NUM_SLAVES{1'b1}}; // Deasserted (active low)
        end else if (master_mode) begin
            // Master mode logic
            if (tx_valid && master_tx_ready_buffer && !master_busy) begin
                // Start new transmission
                master_tx_shift_reg <= tx_data;
                master_tx_ready_buffer <= 1'b0; // Not ready during transmission
                master_busy <= 1'b1;
                master_sclk_en <= 1'b1;
                master_bit_counter <= 8'd0;
                master_sclk_counter <= 8'd0;
                master_start_tx <= 1'b1;
                // Assert slave 0 (active low): all bits high except bit 0
                master_ss_n_reg <= {NUM_SLAVES{1'b1}};
                master_ss_n_reg[0] <= 1'b0;
            end else begin
                master_start_tx <= 1'b0;
            end

            // SPI clock generation and data shifting
            if (master_busy && master_sclk_en) begin
                master_sclk_counter <= master_sclk_counter + 1'b1;

                // Generate SPI clock (divide by CLOCK_DIVIDER)
                if (master_sclk_counter >= CLOCK_DIVIDER) begin
                    master_sclk_counter <= 8'd0;

                    // SPI Mode 0: Sample on rising edge, change on falling edge
                    // For simplicity, we'll toggle and sample on each clock edge
                    if (master_bit_counter < DATA_WIDTH) begin
                        // Shift data
                        if (MSB_FIRST) begin
                            if (DATA_WIDTH > 1) begin
                                master_tx_shift_reg <= {master_tx_shift_reg[DATA_WIDTH-2:0], 1'b0};
                            end else begin
                                master_tx_shift_reg <= 1'b0;  // For 1-bit, just set to 0 after transmission
                            end
                        end else begin
                            if (DATA_WIDTH > 1) begin
                                master_tx_shift_reg <= {1'b0, master_tx_shift_reg[DATA_WIDTH-1:1]};
                            end else begin
                                master_tx_shift_reg <= 1'b0;  // For 1-bit, just set to 0 after transmission
                            end
                        end
                        master_bit_counter <= master_bit_counter + 1'b1;
                    end else begin
                        // Transmission complete
                        master_busy <= 1'b0;
                        master_sclk_en <= 1'b0;
                        master_tx_ready_buffer <= 1'b1; // Ready for next transmission
                        master_rx_valid_buffer <= 1'b1; // Data received
                        master_rx_data_buffer <= master_rx_shift_reg;
                        master_ss_n_reg <= {NUM_SLAVES{1'b1}}; // Deassert slave select
                    end
                end
            end
        end
    end

    // Slave mode implementation - proper SPI protocol handling
    always @(posedge clk or negedge rst_n) begin
        if (!rst_n) begin
            slave_busy_buffer <= 1'b0;
            slave_rx_valid_buffer <= 1'b0;
            slave_tx_ready_buffer <= 1'b0;
            slave_rx_data_buffer <= {DATA_WIDTH{1'b0}};
            slave_tx_shift_reg <= default_data;
            slave_bit_counter <= 8'd0;
            slave_sclk_last_state <= CPOL[0]; // Initialize to CPOL idle state
            slave_ss_last_state <= 1'b1;
            slave_transaction_active <= 1'b0;
            slave_timeout_counter <= 8'd0;
        end else if (!master_mode) begin
            // Detect SS transitions
            slave_ss_last_state <= ss_in;

            // Start transaction on SS falling edge
            if (slave_ss_last_state && !ss_in) begin
                slave_transaction_active <= 1'b1;
                slave_busy_buffer <= 1'b1;
                slave_bit_counter <= 8'd0;
                slave_tx_shift_reg <= tx_data; // Load data to transmit
                slave_tx_ready_buffer <= 1'b0; // Not ready for new data during transaction
            end

            // End transaction on SS rising edge
            if (!slave_ss_last_state && ss_in && slave_transaction_active) begin
                slave_transaction_active <= 1'b0;
                slave_busy_buffer <= 1'b0;
                slave_rx_valid_buffer <= 1'b1; // Data received
                slave_tx_ready_buffer <= 1'b1; // Ready for new transmit data
            end

            // Handle SPI clock edges during active transaction
            if (slave_transaction_active) begin
                slave_sclk_last_state <= sclk_in;
                slave_timeout_counter <= slave_timeout_counter + 1'b1;

                // Timeout mechanism - force completion after ~200 clock cycles
                if (slave_timeout_counter > SLAVE_TIMEOUT_CYCLES) begin
                    slave_transaction_active <= 1'b0;
                    slave_busy_buffer <= 1'b0;
                    slave_rx_valid_buffer <= 1'b1; // Data received (partial)
                    slave_tx_ready_buffer <= 1'b1; // Ready for new transmit data
                    slave_timeout_counter <= 8'd0;
                end else begin
                    // Sample on the correct edge based on SPI mode
                    // SAMPLE_ON_RISING=1 for modes 0,3; =0 for modes 1,2
                    if (SAMPLE_ON_RISING ? (!slave_sclk_last_state && sclk_in) : (slave_sclk_last_state && !sclk_in)) begin
                    // Sample MOSI data
                    if (MSB_FIRST) begin
                        if (DATA_WIDTH > 1) begin
                            slave_rx_data_buffer <= {slave_rx_data_buffer[DATA_WIDTH-2:0], mosi_in};
                        end else begin
                            slave_rx_data_buffer <= mosi_in;  // For 1-bit, just set to received bit
                        end
                    end else begin
                        if (DATA_WIDTH > 1) begin
                            slave_rx_data_buffer <= {mosi_in, slave_rx_data_buffer[DATA_WIDTH-1:1]};
                        end else begin
                            slave_rx_data_buffer <= mosi_in;  // For 1-bit, just set to received bit
                        end
                    end
                        slave_bit_counter <= slave_bit_counter + 1'b1;

                        // Auto-complete transaction after all bits received
                        if (slave_bit_counter >= DATA_WIDTH) begin
                            slave_transaction_active <= 1'b0;
                            slave_busy_buffer <= 1'b0;
                            slave_rx_valid_buffer <= 1'b1; // Data received
                            slave_tx_ready_buffer <= 1'b1; // Ready for new transmit data
                            slave_timeout_counter <= 8'd0;
                        end
                    end
                end
                // Note: MISO changes on falling edge would be handled here if needed
            end else begin
                // Not in transaction
                slave_rx_valid_buffer <= 1'b0;
                slave_tx_ready_buffer <= 1'b1;
                slave_timeout_counter <= 8'd0;
            end
        end
    end

    // Output signal selection based on master_mode
    // SCLK idles at CPOL level; XOR with CPOL inverts the counter parity for correct polarity
    assign sclk = master_mode ? (master_sclk_en ? (master_sclk_counter[0] ^ (CPOL ? 1'b1 : 1'b0)) : (CPOL ? 1'b1 : 1'b0)) : 1'b0;
    assign mosi = master_mode ? master_tx_shift_reg[MSB_FIRST ? DATA_WIDTH-1 : 0] : 1'b0;
    assign miso_out = master_mode ? 1'b0 : (slave_tx_ready_buffer ? default_data[MSB_FIRST ? DATA_WIDTH-1 : 0] : 1'b0);

    // Slave select outputs: active-low, slave 0 asserted during master transmission
    assign ss_n = master_mode ? master_ss_n_reg : {NUM_SLAVES{1'b1}};

    // Data signal selection
    assign rx_data = master_mode ? master_rx_data_buffer : slave_rx_data_buffer;
    assign rx_valid = master_mode ? master_rx_valid_buffer : slave_rx_valid_buffer;
    assign tx_ready = master_mode ? master_tx_ready_buffer : slave_tx_ready_buffer;
    assign busy = master_mode ? master_busy : slave_busy_buffer;

    // Simplified output assignments
    assign irq = 1'b0;  // No interrupts for now

endmodule

results/issue-3/code/spi_dual_tb.v
// =============================================
// SPI Dual Mode Testbench - Auto-generated by SPI Customizer
// =============================================

`timescale 1ns / 1ps

module spi_dual_tb;

    // Parameters
    parameter MODE = 2;
    parameter DATA_WIDTH = 32;
    parameter NUM_SLAVES = 4;
    parameter SLAVE_ACTIVE_LOW = 1;
    parameter MSB_FIRST = 1;
    parameter FIFO_DEPTH = 16;
    parameter MAX_SLAVES = 8;
    parameter CLOCK_DIVIDER = 2;
    parameter DEFAULT_DATA_ENABLED = 0;
    parameter DEFAULT_DATA_VALUE = 32'hA5A5A5A5;

    // Signals
    reg clk;
    reg rst_n;
    reg master_mode;
    wire sclk;
    wire mosi;
    reg miso;
    wire [NUM_SLAVES-1:0] ss_n;
    reg sclk_in;
    reg mosi_in;
    wire miso_out;
    reg ss_in;
    reg [DATA_WIDTH-1:0] tx_data;
    wire [DATA_WIDTH-1:0] rx_data;
    wire rx_valid;
    wire tx_ready;
    reg tx_valid;
    wire busy;
    wire irq;

    // DUT instantiation
    spi_dual #(
        .MODE(MODE),
        .DATA_WIDTH(DATA_WIDTH),
        .NUM_SLAVES(NUM_SLAVES),
        .SLAVE_ACTIVE_LOW(SLAVE_ACTIVE_LOW),
        .MSB_FIRST(MSB_FIRST),
        .FIFO_DEPTH(FIFO_DEPTH),
        .MAX_SLAVES(MAX_SLAVES),
        .CLOCK_DIVIDER(CLOCK_DIVIDER),
        .DEFAULT_DATA_ENABLED(DEFAULT_DATA_ENABLED),
        .DEFAULT_DATA_VALUE(DEFAULT_DATA_VALUE)
    ) dut (
        .clk(clk),
        .rst_n(rst_n),
        .master_mode(master_mode),
        .sclk(sclk),
        .mosi(mosi),
        .miso(miso),
        .ss_n(ss_n),
        .sclk_in(sclk_in),
        .mosi_in(mosi_in),
        .miso_out(miso_out),
        .ss_in(ss_in),
        .rx_data(rx_data),
        .tx_data(tx_data),
        .rx_valid(rx_valid),
        .tx_ready(tx_ready),
        .tx_valid(tx_valid),
        .busy(busy),
        .irq(irq),
        .irq_clear(1'b0)
    );

    // Clock generation
    initial begin
        clk = 0;
        forever #10 clk = ~clk;  // 50MHz clock
    end

    // Test sequence for dual mode
    initial begin
        // Initialize
        rst_n = 0;
        master_mode = 1;  // Start in master mode
        tx_data = 0;
        tx_valid = 0;
        miso = 0;
        sclk_in = (MODE == 2 || MODE == 3) ? 1 : 0; // CPOL idle state
        mosi_in = 0;
        ss_in = 1;

        #100;
        rst_n = 1;
        #200;  // Allow system to stabilize

        $display("=== SPI Dual Mode RTL Testbench Starting ===");
        $display("Configuration: Mode %d, %d-bit data, Dual mode", MODE, DATA_WIDTH);

        // Test master mode first
        $display("--- Testing Master Mode ---");

        // Test basic transmission in master mode
        tx_data = 32'hA5A5A5A5;
        $display("TX Data: 0x%h", tx_data);

        // Wait for tx_ready to be asserted (may already be high)
        wait(tx_ready);
        #10; // Small delay
        tx_valid = 1; // Assert tx_valid to start transmission
        #20; // Hold tx_valid for a few cycles
        tx_valid = 0; // Deassert tx_valid

        // Wait for transmission to complete (with timeout)
        begin : wait_master
            localparam MASTER_TX_TIMEOUT_CYCLES = 5000;
            integer timeout;
            timeout = 0;
            while (!tx_ready && timeout < MASTER_TX_TIMEOUT_CYCLES) begin
                #20;
                timeout = timeout + 1;
            end
            if (timeout >= MASTER_TX_TIMEOUT_CYCLES)
                $display("WARNING: Master transmission timeout");
            else
                $display("Master transmission complete");
        end

        // Switch to slave mode after master test
        #500;
        master_mode = 0;
        $display("--- Switched to Slave Mode ---");

        // Test slave mode with proper SPI master simulation
        #100;

        // Simulate a complete SPI transaction as master to our slave
        $display("Simulating SPI master transaction to test slave mode");

        // Start transaction: assert SS low
        ss_in = 0;
        $display("Slave selected (SS asserted low)");

        // SPI Mode 2: CPOL=1, CPHA=0
        // Sampling occurs on falling edge

        // Send 7 bits of test data (0x5A pattern, MSB first = 0101 1010)
        
        // CPHA=0: data is already valid at SS assertion, clock from idle
        mosi_in = 0; // Bit 6 (MSB of 0x5A = 0101_1010)
        #50;
        sclk_in = 0; // First edge (sampling edge)
        #50;
        sclk_in = 1; // Return to idle

        mosi_in = 1; // Bit 5
        #50;
        sclk_in = 0; // Sampling edge
        #50;
        sclk_in = 1; // Return to idle

        mosi_in = 0; // Bit 4
        #50;
        sclk_in = 0; // Sampling edge
        #50;
        sclk_in = 1; // Return to idle

        mosi_in = 1; // Bit 3
        #50;
        sclk_in = 0; // Sampling edge
        #50;
        sclk_in = 1; // Return to idle

        mosi_in = 1; // Bit 2
        #50;
        sclk_in = 0; // Sampling edge
        #50;
        sclk_in = 1; // Return to idle

        mosi_in = 0; // Bit 1
        #50;
        sclk_in = 0; // Sampling edge
        #50;
        sclk_in = 1; // Return to idle

        mosi_in = 1; // Bit 0 (LSB)
        #50;
        sclk_in = 0; // Sampling edge
        #50;
        sclk_in = 1; // Return to idle
        

        // Return clock to idle
        sclk_in = (MODE == 2 || MODE == 3) ? 1 : 0;

        // End transaction: deassert SS
        #100;
        ss_in = 1;
        $display("Slave mode SPI transaction complete - sent 0x5A (7 bits)");

        #200; // Allow slave to process

        $display("=== All Dual Mode Tests Completed Successfully ===");
        #100; // Small delay before finish
        $finish;
    end

    // VCD dumping
    initial begin
        $dumpfile("results/issue-3/data/spi_waveform.vcd");
        $dumpvars(0, spi_dual_tb);
    end

endmodule

results/issue-3/data/spi_waveform.vcd
$date
	Tue Mar 17 16:40:02 2026
$end
$version
	Icarus Verilog
$end
$timescale
	1ps
$end
$scope module spi_dual_tb $end
$var wire 1 ! irq $end
$var wire 1 " tx_ready $end
$var wire 4 # ss_n [3:0] $end
$var wire 1 $ sclk $end
$var wire 1 % rx_valid $end
$var wire 32 & rx_data [31:0] $end
$var wire 1 ' mosi $end
$var wire 1 ( miso_out $end
$var wire 1 ) busy $end
$var parameter 32 * CLOCK_DIVIDER $end
$var parameter 32 + DATA_WIDTH $end
$var parameter 32 , DEFAULT_DATA_ENABLED $end
$var parameter 32 - DEFAULT_DATA_VALUE $end
$var parameter 32 . FIFO_DEPTH $end
$var parameter 32 / MAX_SLAVES $end
$var parameter 32 0 MODE $end
$var parameter 32 1 MSB_FIRST $end
$var parameter 32 2 NUM_SLAVES $end
$var parameter 32 3 SLAVE_ACTIVE_LOW $end
$var reg 1 4 clk $end
$var reg 1 5 master_mode $end
$var reg 1 6 miso $end
$var reg 1 7 mosi_in $end
$var reg 1 8 rst_n $end
$var reg 1 9 sclk_in $end
$var reg 1 : ss_in $end
$var reg 32 ; tx_data [31:0] $end
$var reg 1 < tx_valid $end
$scope module dut $end
$var wire 1 4 clk $end
$var wire 1 ! irq $end
$var wire 1 = irq_clear $end
$var wire 1 5 master_mode $end
$var wire 1 6 miso $end
$var wire 1 7 mosi_in $end
$var wire 1 8 rst_n $end
$var wire 1 9 sclk_in $end
$var wire 1 : ss_in $end
$var wire 32 > tx_data [31:0] $end
$var wire 1 < tx_valid $end
$var wire 1 " tx_ready $end
$var wire 4 ? ss_n [3:0] $end
$var wire 1 $ sclk $end
$var wire 1 % rx_valid $end
$var wire 32 @ rx_data [31:0] $end
$var wire 1 ' mosi $end
$var wire 1 ( miso_out $end
$var wire 1 ) busy $end
$var parameter 32 A CLOCK_DIVIDER $end
$var parameter 32 B CPOL $end
$var parameter 32 C DATA_WIDTH $end
$var parameter 32 D DEFAULT_DATA_ENABLED $end
$var parameter 32 E DEFAULT_DATA_VALUE $end
$var parameter 32 F FIFO_DEPTH $end
$var parameter 32 G MAX_SLAVES $end
$var parameter 32 H MODE $end
$var parameter 32 I MSB_FIRST $end
$var parameter 32 J NUM_SLAVES $end
$var parameter 32 K SAMPLE_ON_RISING $end
$var parameter 32 L SLAVE_ACTIVE_LOW $end
$var parameter 8 M SLAVE_TIMEOUT_CYCLES $end
$var reg 32 N default_data [31:0] $end
$var reg 8 O master_bit_counter [7:0] $end
$var reg 1 P master_busy $end
$var reg 32 Q master_rx_data_buffer [31:0] $end
$var reg 32 R master_rx_shift_reg [31:0] $end
$var reg 1 S master_rx_valid_buffer $end
$var reg 8 T master_sclk_counter [7:0] $end
$var reg 1 U master_sclk_en $end
$var reg 4 V master_ss_n_reg [3:0] $end
$var reg 1 W master_start_rx $end
$var reg 1 X master_start_tx $end
$var reg 1 Y master_tx_ready_buffer $end
$var reg 32 Z master_tx_shift_reg [31:0] $end
$var reg 8 [ slave_bit_counter [7:0] $end
$var reg 1 \ slave_busy_buffer $end
$var reg 32 ] slave_rx_data_buffer [31:0] $end
$var reg 1 ^ slave_rx_valid_buffer $end
$var reg 1 _ slave_sclk_last_state $end
$var reg 1 ` slave_ss_last_state $end
$var reg 8 a slave_timeout_counter [7:0] $end
$var reg 1 b slave_transaction_active $end
$var reg 1 c slave_tx_ready_buffer $end
$var reg 32 d slave_tx_shift_reg [31:0] $end
$upscope $end
$scope begin wait_master $end
$var parameter 32 e MASTER_TX_TIMEOUT_CYCLES $end
$var integer 32 f timeout [31:0] $end
$upscope $end
$upscope $end
$enddefinitions $end
$comment Show the parameter values. $end
$dumpall
b1001110001000 e
b11001000 M
b1 L
b0 K
b100 J
b1 I
b10 H
b1000 G
b10000 F
b10100101101001011010010110100101 E
b0 D
b100000 C
b1 B
b10 A
b1 3
b100 2
b1 1
b10 0
b1000 /
b10000 .
b10100101101001011010010110100101 -
b0 ,
b100000 +
b10 *
$end
#0
$dumpvars
bx f
bx d
0c
0b
b0 a
1`
1_
0^
b0 ]
0\
b0 [
b0 Z
1Y
0X
0W
b1111 V
0U
b0 T
0S
b0 R
bx Q
0P
b0 O
b10100101101001011010010110100101 N
bx @
b1111 ?
b0 >
0=
0<
b0 ;
1:
19
08
07
06
15
04
0)
0(
0'
bx &
0%
1$
b1111 #
1"
0!
$end
#10000
b10100101101001011010010110100101 d
14
#20000
04
#30000
14
#40000
04
#50000
14
#60000
04
#70000
14
#80000
04
#90000
14
#100000
04
18
#110000
14
#120000
04
#130000
14
#140000
04
#150000
14
#160000
04
#170000
14
#180000
04
#190000
14
#200000
04
#210000
14
#220000
04
#230000
14
#240000
04
#250000
14
#260000
04
#270000
14
#280000
04
#290000
14
#300000
04
b10100101101001011010010110100101 ;
b10100101101001011010010110100101 >
#310000
1'
b1110 #
b1110 ?
1)
0"
b1110 V
1X
1U
1P
0Y
b10100101101001011010010110100101 Z
14
1<
#320000
04
#330000
0$
b1 T
0X
14
b0 f
0<
#340000
04
#350000
1$
b10 T
14
b1 f
#360000
04
#370000
0'
b1 O
b1001011010010110100101101001010 Z
b0 T
14
b10 f
#380000
04
#390000
0$
b1 T
14
b11 f
#400000
04
#410000
1$
b10 T
14
b100 f
#420000
04
#430000
1'
b10 O
b10010110100101101001011010010100 Z
b0 T
14
b101 f
#440000
04
#450000
0$
b1 T
14
b110 f
#460000
04
#470000
1$
b10 T
14
b111 f
#480000
04
#490000
0'
b11 O
b101101001011010010110100101000 Z
b0 T
14
b1000 f
#500000
04
#510000
0$
b1 T
14
b1001 f
#520000
04
#530000
1$
b10 T
14
b1010 f
#540000
04
#550000
b100 O
b1011010010110100101101001010000 Z
b0 T
14
b1011 f
#560000
04
#570000
0$
b1 T
14
b1100 f
#580000
04
#590000
1$
b10 T
14
b1101 f
#600000
04
#610000
1'
b101 O
b10110100101101001011010010100000 Z
b0 T
14
b1110 f
#620000
04
#630000
0$
b1 T
14
b1111 f
#640000
04
#650000
1$
b10 T
14
b10000 f
#660000
04
#670000
0'
b110 O
b1101001011010010110100101000000 Z
b0 T
14
b10001 f
#680000
04
#690000
0$
b1 T
14
b10010 f
#700000
04
#710000
1$
b10 T
14
b10011 f
#720000
04
#730000
1'
b111 O
b11010010110100101101001010000000 Z
b0 T
14
b10100 f
#740000
04
#750000
0$
b1 T
14
b10101 f
#760000
04
#770000
1$
b10 T
14
b10110 f
#780000
04
#790000
b1000 O
b10100101101001011010010100000000 Z
b0 T
14
b10111 f
#800000
04
#810000
0$
b1 T
14
b11000 f
#820000
04
#830000
1$
b10 T
14
b11001 f
#840000
04
#850000
0'
b1001 O
b1001011010010110100101000000000 Z
b0 T
14
b11010 f
#860000
04
#870000
0$
b1 T
14
b11011 f
#880000
04
#890000
1$
b10 T
14
b11100 f
#900000
04
#910000
1'
b1010 O
b10010110100101101001010000000000 Z
b0 T
14
b11101 f
#920000
04
#930000
0$
b1 T
14
b11110 f
#940000
04
#950000
1$
b10 T
14
b11111 f
#960000
04
#970000
0'
b1011 O
b101101001011010010100000000000 Z
b0 T
14
b100000 f
#980000
04
#990000
0$
b1 T
14
b100001 f
#1000000
04
#1010000
1$
b10 T
14
b100010 f
#1020000
04
#1030000
b1100 O
b1011010010110100101000000000000 Z
b0 T
14
b100011 f
#1040000
04
#1050000
0$
b1 T
14
b100100 f
#1060000
04
#1070000
1$
b10 T
14
b100101 f
#1080000
04
#1090000
1'
b1101 O
b10110100101101001010000000000000 Z
b0 T
14
b100110 f
#1100000
04
#1110000
0$
b1 T
14
b100111 f
#1120000
04
#1130000
1$
b10 T
14
b101000 f
#1140000
04
#1150000
0'
b1110 O
b1101001011010010100000000000000 Z
b0 T
14
b101001 f
#1160000
04
#1170000
0$
b1 T
14
b101010 f
#1180000
04
#1190000
1$
b10 T
14
b101011 f
#1200000
04
#1210000
1'
b1111 O
b11010010110100101000000000000000 Z
b0 T
14
b101100 f
#1220000
04
#1230000
0$
b1 T
14
b101101 f
#1240000
04
#1250000
1$
b10 T
14
b101110 f
#1260000
04
#1270000
b10000 O
b10100101101001010000000000000000 Z
b0 T
14
b101111 f
#1280000
04
#1290000
0$
b1 T
14
b110000 f
#1300000
04
#1310000
1$
b10 T
14
b110001 f
#1320000
04
#1330000
0'
b10001 O
b1001011010010100000000000000000 Z
b0 T
14
b110010 f
#1340000
04
#1350000
0$
b1 T
14
b110011 f
#1360000
04
#1370000
1$
b10 T
14
b110100 f
#1380000
04
#1390000
1'
b10010 O
b10010110100101000000000000000000 Z
b0 T
14
b110101 f
#1400000
04
#1410000
0$
b1 T
14
b110110 f
#1420000
04
#1430000
1$
b10 T
14
b110111 f
#1440000
04
#1450000
0'
b10011 O
b101101001010000000000000000000 Z
b0 T
14
b111000 f
#1460000
04
#1470000
0$
b1 T
14
b111001 f
#1480000
04
#1490000
1$
b10 T
14
b111010 f
#1500000
04
#1510000
b10100 O
b1011010010100000000000000000000 Z
b0 T
14
b111011 f
#1520000
04
#1530000
0$
b1 T
14
b111100 f
#1540000
04
#1550000
1$
b10 T
14
b111101 f
#1560000
04
#1570000
1'
b10101 O
b10110100101000000000000000000000 Z
b0 T
14
b111110 f
#1580000
04
#1590000
0$
b1 T
14
b111111 f
#1600000
04
#1610000
1$
b10 T
14
b1000000 f
#1620000
04
#1630000
0'
b10110 O
b1101001010000000000000000000000 Z
b0 T
14
b1000001 f
#1640000
04
#1650000
0$
b1 T
14
b1000010 f
#1660000
04
#1670000
1$
b10 T
14
b1000011 f
#1680000
04
#1690000
1'
b10111 O
b11010010100000000000000000000000 Z
b0 T
14
b1000100 f
#1700000
04
#1710000
0$
b1 T
14
b1000101 f
#1720000
04
#1730000
1$
b10 T
14
b1000110 f
#1740000
04
#1750000
b11000 O
b10100101000000000000000000000000 Z
b0 T
14
b1000111 f
#1760000
04
#1770000
0$
b1 T
14
b1001000 f
#1780000
04
#1790000
1$
b10 T
14
b1001001 f
#1800000
04
#1810000
0'
b11001 O
b1001010000000000000000000000000 Z
b0 T
14
b1001010 f
#1820000
04
#1830000
0$
b1 T
14
b1001011 f
#1840000
04
#1850000
1$
b10 T
14
b1001100 f
#1860000
04
#1870000
1'
b11010 O
b10010100000000000000000000000000 Z
b0 T
14
b1001101 f
#1880000
04
#1890000
0$
b1 T
14
b1001110 f
#1900000
04
#1910000
1$
b10 T
14
b1001111 f
#1920000
04
#1930000
0'
b11011 O
b101000000000000000000000000000 Z
b0 T
14
b1010000 f
#1940000
04
#1950000
0$
b1 T
14
b1010001 f
#1960000
04
#1970000
1$
b10 T
14
b1010010 f
#1980000
04
#1990000
b11100 O
b1010000000000000000000000000000 Z
b0 T
14
b1010011 f
#2000000
04
#2010000
0$
b1 T
14
b1010100 f
#2020000
04
#2030000
1$
b10 T
14
b1010101 f
#2040000
04
#2050000
1'
b11101 O
b10100000000000000000000000000000 Z
b0 T
14
b1010110 f
#2060000
04
#2070000
0$
b1 T
14
b1010111 f
#2080000
04
#2090000
1$
b10 T
14
b1011000 f
#2100000
04
#2110000
0'
b11110 O
b1000000000000000000000000000000 Z
b0 T
14
b1011001 f
#2120000
04
#2130000
0$
b1 T
14
b1011010 f
#2140000
04
#2150000
1$
b10 T
14
b1011011 f
#2160000
04
#2170000
1'
b11111 O
b10000000000000000000000000000000 Z
b0 T
14
b1011100 f
#2180000
04
#2190000
0$
b1 T
14
b1011101 f
#2200000
04
#2210000
1$
b10 T
14
b1011110 f
#2220000
04
#2230000
0'
b100000 O
b0 Z
b0 T
14
b1011111 f
#2240000
04
#2250000
0$
b1 T
14
b1100000 f
#2260000
04
#2270000
1$
b10 T
14
b1100001 f
#2280000
04
#2290000
b1111 #
b1111 ?
b0 &
b0 @
1%
1"
0)
b1111 V
b0 Q
1S
1Y
0U
0P
b0 T
14
b1100010 f
#2300000
04
#2310000
14
b1100011 f
