results/issue-42/code/spi_master_mode2_8bit.v
module spi_master #(
    parameter MODE = 2,              // SPI Mode (0-3)
    parameter DATA_WIDTH = 8,       // Data width in bits
    parameter NUM_SLAVES = 3,        // Number of slave devices
    parameter SLAVE_ACTIVE_LOW = 1,  // Slave select active level
    parameter MSB_FIRST = 1,          // Data transmission order
    parameter FIFO_DEPTH = 16,        // FIFO buffer depth
    parameter CLOCK_DIVIDER = 2,  // System clock divider
    parameter DEFAULT_DATA_ENABLED = 0,
    parameter DEFAULT_DATA_PATTERN = "Custom",
    parameter DEFAULT_DATA_VALUE = 8'he
)(
    input  wire                  clk,        // System clock
    input  wire                  rst_n,      // Active low reset

    // Control interface
    input  wire                  start_tx,   // Start transmission
    input  wire                  start_rx,   // Start reception
    input  wire [DATA_WIDTH-1:0] tx_data,    // Data to transmit
    output reg  [DATA_WIDTH-1:0] rx_data,    // Received data
    output reg                   busy,       // Busy signal

    // SPI interface
    output reg                   sclk,       // SPI clock
    output reg                   mosi,       // Master out, slave in
    input  wire                  miso,       // Master in, slave out
    output reg [NUM_SLAVES-1:0]  ss_n,       // Slave select (active low)

    // Interrupt (optional)
    output reg                   irq         // Interrupt request
);

    // Local parameters
    localparam SCLK_HALF_PERIOD = CLOCK_DIVIDER; // Configurable SCLK period based on system clock

    // State machine states
    localparam IDLE = 3'd0;
    localparam SETUP = 3'd1;
    localparam TRANSMIT = 3'd2;
    localparam RECEIVE = 3'd3;
    localparam COMPLETE = 3'd4;

    // Registers
    reg [2:0]  state;
    reg [2:0]  next_state;
    reg [15:0] clk_counter;    // SCLK generation counter
    reg [4:0]  bit_counter;    // Bit transmission counter
    reg [DATA_WIDTH-1:0] tx_shift_reg;
    reg [DATA_WIDTH-1:0] rx_shift_reg;
    reg        sclk_gen;       // SCLK generator
    reg        last_sclk;      // Previous SCLK value for edge detection

    // Clock polarity and phase for different modes
    wire CPOL = (MODE == 2) || (MODE == 3);  // Clock polarity
    wire CPHA = (MODE == 1) || (MODE == 3);  // Clock phase

    // Slave select active level
    wire SS_ACTIVE = SLAVE_ACTIVE_LOW ? 1'b0 : 1'b1;

    // Default data generation
    reg [DATA_WIDTH-1:0] default_data;
    always @(posedge clk or negedge rst_n) begin
        if (!rst_n) begin
            default_data <= 8'he;
        end else if (DEFAULT_DATA_ENABLED) begin
            case (DEFAULT_DATA_PATTERN)
                "a5a5": default_data <= 8'hA5A5;
                "ffff": default_data <= 8'hFFFF;
                "0000": default_data <= 8'h0000;
                "5555": default_data <= 8'h5555;
                default: default_data <= 8'he;
            endcase
        end
    end

    // State machine
    always @(posedge clk or negedge rst_n) begin
        if (!rst_n) begin
            state <= IDLE;
            clk_counter <= 0;
            bit_counter <= 0;
            tx_shift_reg <= 0;
            rx_shift_reg <= 0;
            sclk <= CPOL;  // Set initial SCLK state based on CPOL
            mosi <= 0;
            ss_n <= {NUM_SLAVES{1'b1}};
            busy <= 0;
            irq <= 0;
            last_sclk <= CPOL;
        end else begin
            state <= next_state;
            last_sclk <= sclk_gen;

            // State-specific register updates
            case (state)
                IDLE: begin
                    // Clear interrupt when acknowledged (optional)
                    if (irq) begin
                        irq <= 0;
                    end
                end

                SETUP: begin
                    // Initialize transmission
                    bit_counter <= 0;
                    tx_shift_reg <= DEFAULT_DATA_ENABLED ? default_data : tx_data;
                    rx_shift_reg <= 0;
                end

                COMPLETE: begin
                    // Capture received data
                    rx_data <= rx_shift_reg;
                end
            endcase

            // SCLK generation (runs during active transmission/reception)
            if (state == TRANSMIT || state == RECEIVE) begin
                if (clk_counter >= SCLK_HALF_PERIOD - 1) begin
                    clk_counter <= 0;
                    sclk_gen <= ~sclk_gen;
                end else begin
                    clk_counter <= clk_counter + 1;
                end
            end else begin
                clk_counter <= 0;
                sclk_gen <= CPOL;
            end

            // Data transmission and reception (runs during TRANSMIT/RECEIVE)
            if (state == TRANSMIT || state == RECEIVE) begin
                // Sample data on appropriate edge
                if (CPHA == 0) begin
                    // Sample on leading edge (CPOL to ~CPOL transition)
                    if (sclk_gen != last_sclk && sclk_gen == ~CPOL) begin
                        if (bit_counter < DATA_WIDTH) begin
                            // Shift in received data
                            if (MSB_FIRST) begin
                                rx_shift_reg <= {rx_shift_reg[DATA_WIDTH-2:0], miso};
                            end else begin
                                rx_shift_reg <= {miso, rx_shift_reg[DATA_WIDTH-1:1]};
                            end

                            // Shift out transmitted data
                            if (MSB_FIRST) begin
                                mosi <= tx_shift_reg[DATA_WIDTH-1];
                                tx_shift_reg <= {tx_shift_reg[DATA_WIDTH-2:0], 1'b0};
                            end else begin
                                mosi <= tx_shift_reg[0];
                                tx_shift_reg <= {1'b0, tx_shift_reg[DATA_WIDTH-1:1]};
                            end

                            bit_counter <= bit_counter + 1;
                        end
                    end
                end else begin
                    // Sample on trailing edge (CPOL transition)
                    if (sclk_gen != last_sclk && sclk_gen == CPOL) begin
                        if (bit_counter < DATA_WIDTH) begin
                            // Shift in received data
                            if (MSB_FIRST) begin
                                rx_shift_reg <= {rx_shift_reg[DATA_WIDTH-2:0], miso};
                            end else begin
                                rx_shift_reg <= {miso, rx_shift_reg[DATA_WIDTH-1:1]};
                            end

                            // Shift out transmitted data
                            if (MSB_FIRST) begin
                                mosi <= tx_shift_reg[DATA_WIDTH-1];
                                tx_shift_reg <= {tx_shift_reg[DATA_WIDTH-2:0], 1'b0};
                            end else begin
                                mosi <= tx_shift_reg[0];
                                tx_shift_reg <= {1'b0, tx_shift_reg[DATA_WIDTH-1:1]};
                            end

                            bit_counter <= bit_counter + 1;
                        end
                    end
                end
            end
        end
    end

    // SCLK output assignment
    always @(posedge clk or negedge rst_n) begin
        if (!rst_n) begin
            sclk <= CPOL;
        end else begin
            sclk <= sclk_gen;
        end
    end

    // Next state logic
    always @(*) begin
        next_state = state;

        case (state)
            IDLE: begin
                if (start_tx) begin
                    next_state = SETUP;
                end else if (start_rx) begin
                    next_state = SETUP;
                end
            end

            SETUP: begin
                next_state = TRANSMIT;
            end

            TRANSMIT: begin
                if (bit_counter >= DATA_WIDTH) begin
                    next_state = COMPLETE;
                end
            end

            RECEIVE: begin
                if (bit_counter >= DATA_WIDTH) begin
                    next_state = COMPLETE;
                end
            end

            COMPLETE: begin
                next_state = IDLE;
            end

            default: next_state = IDLE;
        endcase
    end

    // Output logic
    always @(*) begin
        case (state)
            IDLE: begin
                busy = 0;
                irq = 0;
                ss_n = {NUM_SLAVES{1'b1}};
            end

            SETUP: begin
                busy = 1;
                ss_n = {NUM_SLAVES{SS_ACTIVE}};  // Activate slave select
            end

            TRANSMIT: begin
                busy = 1;
                ss_n = {NUM_SLAVES{SS_ACTIVE}};  // Keep slave select active
            end

            RECEIVE: begin
                busy = 1;
                ss_n = {NUM_SLAVES{SS_ACTIVE}};  // Keep slave select active
            end

            COMPLETE: begin
                busy = 0;
                ss_n = {NUM_SLAVES{1'b1}};  // Deactivate slave select
                irq = 1;  // Generate interrupt
            end

            default: begin
                busy = 0;
                irq = 0;
                ss_n = {NUM_SLAVES{1'b1}};
            end
        endcase
    end

endmodule

results/issue-42/code/spi_master_tb.v
// =============================================
// SPI Master Testbench - Auto-generated by SPI Customizer
// =============================================

`timescale 1ns / 1ps

module spi_master_tb;

    // Parameters
    parameter MODE = 2;
    parameter DATA_WIDTH = 8;
    parameter NUM_SLAVES = 3;
    parameter SLAVE_ACTIVE_LOW = 1;
    parameter MSB_FIRST = 1;
    parameter FIFO_DEPTH = 16;
    parameter CLOCK_DIVIDER = 2;
    parameter DEFAULT_DATA_ENABLED = 0;
    parameter DEFAULT_DATA_PATTERN = "Custom";
    parameter DEFAULT_DATA_VALUE = 16'he;

    // Signals
    reg clk;
    reg rst_n;
    reg start_tx;
    reg start_rx;
    reg [DATA_WIDTH-1:0] tx_data;
    wire [DATA_WIDTH-1:0] rx_data;
    wire busy;
    wire sclk;
    wire mosi;
    reg miso;
    wire [NUM_SLAVES-1:0] ss_n;
    wire irq;

    // DUT instantiation
    spi_master #(
        .MODE(MODE),
        .DATA_WIDTH(DATA_WIDTH),
        .NUM_SLAVES(NUM_SLAVES),
        .SLAVE_ACTIVE_LOW(SLAVE_ACTIVE_LOW),
        .MSB_FIRST(MSB_FIRST),
        .FIFO_DEPTH(FIFO_DEPTH),
        .CLOCK_DIVIDER(CLOCK_DIVIDER),
        .DEFAULT_DATA_ENABLED(DEFAULT_DATA_ENABLED),
        .DEFAULT_DATA_PATTERN(DEFAULT_DATA_PATTERN),
        .DEFAULT_DATA_VALUE(DEFAULT_DATA_VALUE)
    ) dut (
        .clk(clk),
        .rst_n(rst_n),
        .start_tx(start_tx),
        .start_rx(start_rx),
        .tx_data(tx_data),
        .rx_data(rx_data),
        .busy(busy),
        .sclk(sclk),
        .mosi(mosi),
        .miso(miso),
        .ss_n(ss_n),
        .irq(irq)
    );

    // Clock generation
    initial begin
        clk = 0;
        forever #10 clk = ~clk;  // 50MHz clock
    end

    // Test sequence for master mode
    initial begin
        // Initialize
        rst_n = 0;
        start_tx = 0;
        start_rx = 0;
        tx_data = 0;
        miso = 0;

        #100;
        rst_n = 1;
        #200;  // Allow system to stabilize

        $display("=== SPI Master RTL Testbench Starting ===");
        $display("Configuration: Mode %d, %d-bit data, %d slaves", MODE, DATA_WIDTH, NUM_SLAVES);

        // Test core SPI functionality (optimized for speed)
        $display("--- Testing Core SPI Functionality ---");

        // Test 1: Basic data transmission
        
        
        tx_data = 8'hA5;
        
        $display("TX Data: 0x%h", tx_data);
        start_tx = 1;
        #50;
        start_tx = 0;

        wait (!busy);
        $display("✓ Transmission complete");

        // Brief delay between transactions
        #200;
        

        // Test 2: Different data pattern (test MSB/LSB order)
        
        tx_data = 8'h55;
        
        $display("TX Data: 0x%h", tx_data);
        start_tx = 1;
        #50;
        start_tx = 0;

        wait (!busy);
        $display("✓ Second transmission complete");

        // Test reception (simplified for speed)
        $display("--- Testing Reception ---");

        
        // Prepare to receive data from slave 0
        start_rx = 1;
        #50;
        start_rx = 0;

        // Simulate slave providing response data
        #200;
        miso = 1'b0;  // Data bit based on CPHA

        wait (!busy);
        $display("✓ Reception complete");
        

        // Test 3: Quick burst transmission (simplified)
        $display("--- Testing Burst Transmission ---");
        tx_data = 8'hF0;
        $display("Burst TX: 0x%h", tx_data);
        start_tx = 1;
        #30;
        start_tx = 0;

        wait (!busy);
        $display("✓ Burst transmission complete");

        // Test 4: Quick configuration test
        $display("--- Testing Configuration ---");
        
        tx_data = 8'hAB;
        
        $display("Config TX: 0x%h", tx_data);
        start_tx = 1;
        #30;
        start_tx = 0;

        wait (!busy);
        $display("✓ Configuration test complete");

        $display("=== All Master Tests Completed Successfully ===");
        $finish;
    end

    // VCD dumping
    initial begin
        $dumpfile("results/issue-42/data/spi_waveform.vcd");
        $dumpvars(0, spi_master_tb);
    end

endmodule

results/issue-42/data/spi_waveform.vcd
$date
	Tue Oct 14 16:13:53 2025
$end
$version
	Icarus Verilog
$end
$timescale
	1ps
$end
$scope module spi_master_tb $end
$var wire 3 ! ss_n [2:0] $end
$var wire 1 " sclk $end
$var wire 8 # rx_data [7:0] $end
$var wire 1 $ mosi $end
$var wire 1 % irq $end
$var wire 1 & busy $end
$var parameter 32 ' CLOCK_DIVIDER $end
$var parameter 32 ( DATA_WIDTH $end
$var parameter 32 ) DEFAULT_DATA_ENABLED $end
$var parameter 48 * DEFAULT_DATA_PATTERN $end
$var parameter 16 + DEFAULT_DATA_VALUE $end
$var parameter 32 , FIFO_DEPTH $end
$var parameter 32 - MODE $end
$var parameter 32 . MSB_FIRST $end
$var parameter 32 / NUM_SLAVES $end
$var parameter 32 0 SLAVE_ACTIVE_LOW $end
$var reg 1 1 clk $end
$var reg 1 2 miso $end
$var reg 1 3 rst_n $end
$var reg 1 4 start_rx $end
$var reg 1 5 start_tx $end
$var reg 8 6 tx_data [7:0] $end
$scope module dut $end
$var wire 1 7 CPHA $end
$var wire 1 8 CPOL $end
$var wire 1 9 SS_ACTIVE $end
$var wire 1 1 clk $end
$var wire 1 2 miso $end
$var wire 1 3 rst_n $end
$var wire 1 4 start_rx $end
$var wire 1 5 start_tx $end
$var wire 8 : tx_data [7:0] $end
$var parameter 32 ; CLOCK_DIVIDER $end
$var parameter 3 < COMPLETE $end
$var parameter 32 = DATA_WIDTH $end
$var parameter 32 > DEFAULT_DATA_ENABLED $end
$var parameter 48 ? DEFAULT_DATA_PATTERN $end
$var parameter 16 @ DEFAULT_DATA_VALUE $end
$var parameter 32 A FIFO_DEPTH $end
$var parameter 3 B IDLE $end
$var parameter 32 C MODE $end
$var parameter 32 D MSB_FIRST $end
$var parameter 32 E NUM_SLAVES $end
$var parameter 3 F RECEIVE $end
$var parameter 32 G SCLK_HALF_PERIOD $end
$var parameter 3 H SETUP $end
$var parameter 32 I SLAVE_ACTIVE_LOW $end
$var parameter 3 J TRANSMIT $end
$var reg 5 K bit_counter [4:0] $end
$var reg 1 & busy $end
$var reg 16 L clk_counter [15:0] $end
$var reg 8 M default_data [7:0] $end
$var reg 1 % irq $end
$var reg 1 N last_sclk $end
$var reg 1 $ mosi $end
$var reg 3 O next_state [2:0] $end
$var reg 8 P rx_data [7:0] $end
$var reg 8 Q rx_shift_reg [7:0] $end
$var reg 1 " sclk $end
$var reg 1 R sclk_gen $end
$var reg 3 S ss_n [2:0] $end
$var reg 3 T state [2:0] $end
$var reg 8 U tx_shift_reg [7:0] $end
$upscope $end
$upscope $end
$enddefinitions $end
$comment Show the parameter values. $end
$dumpall
b10 J
b1 I
b1 H
b10 G
b11 F
b11 E
b1 D
b10 C
b0 B
b10000 A
b1110 @
b10000110111010101110011011101000110111101101101 ?
b0 >
b1000 =
b100 <
b10 ;
b1 0
b11 /
b1 .
b10 -
b10000 ,
b1110 +
b10000110111010101110011011101000110111101101101 *
b0 )
b1000 (
b10 '
$end
#0
$dumpvars
b0 U
b0 T
b111 S
xR
b0 Q
bx P
b0 O
1N
b1110 M
b0 L
b0 K
b0 :
09
18
07
b0 6
05
04
03
02
01
0&
0%
0$
bx #
1"
b111 !
$end
#10000
11
#20000
01
#30000
11
#40000
01
#50000
11
#60000
01
#70000
11
#80000
01
#90000
11
#100000
01
13
#110000
1R
xN
x"
11
#120000
01
#130000
1"
1N
11
#140000
01
#150000
11
#160000
01
#170000
11
#180000
01
#190000
11
#200000
01
#210000
11
#220000
01
#230000
11
#240000
01
#250000
11
#260000
01
#270000
11
#280000
01
#290000
11
#300000
b1 O
01
15
b10100101 6
b10100101 :
#310000
b0 !
b0 S
1&
b10 O
b1 T
11
#320000
01
#330000
b10100101 U
b10 T
11
#340000
01
#350000
b1 L
11
05
#360000
01
#370000
0R
b0 L
11
#380000
01
#390000
b1 K
b1001010 U
1$
b1 L
0N
0"
11
#400000
01
#410000
1R
b0 L
11
#420000
01
#430000
b1 L
1N
1"
11
#440000
01
#450000
0R
b0 L
11
#460000
01
#470000
b10 K
b10010100 U
0$
b1 L
0N
0"
11
#480000
01
#490000
1R
b0 L
11
#500000
01
#510000
b1 L
1N
1"
11
#520000
01
#530000
0R
b0 L
11
#540000
01
#550000
b11 K
b101000 U
1$
b1 L
0N
0"
11
#560000
01
#570000
1R
b0 L
11
#580000
01
#590000
b1 L
1N
1"
11
#600000
01
#610000
0R
b0 L
11
#620000
01
#630000
b100 K
b1010000 U
0$
b1 L
0N
0"
11
#640000
01
#650000
1R
b0 L
11
#660000
01
#670000
b1 L
1N
1"
11
#680000
01
#690000
0R
b0 L
11
#700000
01
#710000
b101 K
b10100000 U
b1 L
0N
0"
11
#720000
01
#730000
1R
b0 L
11
#740000
01
#750000
b1 L
1N
1"
11
#760000
01
#770000
0R
b0 L
11
#780000
01
#790000
b110 K
b1000000 U
1$
b1 L
0N
0"
11
#800000
01
#810000
1R
b0 L
11
#820000
01
#830000
b1 L
1N
1"
11
#840000
01
#850000
0R
b0 L
11
#860000
01
#870000
b111 K
b10000000 U
0$
b1 L
0N
0"
11
#880000
01
#890000
1R
b0 L
11
#900000
01
#910000
b1 L
1N
1"
11
#920000
01
#930000
0R
b0 L
11
#940000
01
#950000
b100 O
b1000 K
b0 U
1$
b1 L
0N
0"
11
#960000
01
#970000
1%
b111 !
b111 S
0&
b0 O
1R
b0 L
b100 T
11
#980000
01
#990000
0%
b0 #
b0 P
1N
b0 T
1"
11
#1000000
01
#1010000
11
#1020000
01
#1030000
11
#1040000
01
#1050000
11
#1060000
01
#1070000
11
#1080000
01
#1090000
11
#1100000
01
#1110000
11
#1120000
01
#1130000
11
#1140000
01
#1150000
11
#1160000
01
#1170000
b0 !
b0 S
1&
b1 T
b10 O
11
15
b1010101 6
b1010101 :
#1180000
01
#1190000
b1010101 U
b0 K
b10 T
11
#1200000
01
#1210000
b1 L
11
#1220000
01
05
#1230000
0R
b0 L
11
#1240000
01
#1250000
0"
b1 K
b10101010 U
0$
b1 L
0N
11
#1260000
01
#1270000
1R
b0 L
11
#1280000
01
#1290000
1"
b1 L
1N
11
#1300000
01
#1310000
0R
b0 L
11
#1320000
01
#1330000
0"
b10 K
b1010100 U
1$
b1 L
0N
11
#1340000
01
#1350000
1R
b0 L
11
#1360000
01
#1370000
1"
b1 L
1N
11
#1380000
01
#1390000
0R
b0 L
11
#1400000
01
#1410000
0"
b11 K
b10101000 U
0$
b1 L
0N
11
#1420000
01
#1430000
1R
b0 L
11
#1440000
01
#1450000
1"
b1 L
1N
11
#1460000
01
#1470000
0R
b0 L
11
#1480000
01
#1490000
0"
b100 K
b1010000 U
1$
b1 L
0N
11
#1500000
01
#1510000
1R
b0 L
11
#1520000
01
#1530000
1"
b1 L
1N
11
#1540000
01
#1550000
0R
b0 L
11
#1560000
01
#1570000
0"
b101 K
b10100000 U
0$
b1 L
0N
11
#1580000
01
#1590000
1R
b0 L
11
#1600000
01
#1610000
1"
b1 L
1N
11
#1620000
01
#1630000
0R
b0 L
11
#1640000
01
#1650000
0"
b110 K
b1000000 U
1$
b1 L
0N
11
#1660000
01
#1670000
1R
b0 L
11
#1680000
01
#1690000
1"
b1 L
1N
11
#1700000
01
#1710000
0R
b0 L
11
#1720000
01
#1730000
0"
b111 K
b10000000 U
0$
b1 L
0N
11
#1740000
01
#1750000
1R
b0 L
11
#1760000
01
#1770000
1"
b1 L
1N
11
#1780000
01
#1790000
0R
b0 L
11
#1800000
01
#1810000
b100 O
0"
b1000 K
b0 U
1$
b1 L
0N
11
#1820000
01
#1830000
14
1%
b111 !
b111 S
0&
b0 O
1R
b0 L
b100 T
11
#1840000
01
#1850000
0%
b1 O
1"
1N
b0 T
11
#1860000
01
#1870000
b0 !
b0 S
1&
b10 O
b1 T
11
#1880000
b10 O
01
04
#1890000
b1010101 U
b0 K
b10 T
11
#1900000
01
#1910000
b1 L
11
#1920000
01
#1930000
0R
b0 L
11
#1940000
01
#1950000
b1 K
b10101010 U
0$
b1 L
0N
0"
11
#1960000
01
#1970000
1R
b0 L
11
#1980000
01
#1990000
b1 L
1N
1"
11
#2000000
01
#2010000
0R
b0 L
11
#2020000
01
#2030000
b10 K
b1010100 U
1$
b1 L
0N
0"
11
#2040000
01
#2050000
1R
b0 L
11
#2060000
01
#2070000
b1 L
1N
1"
11
#2080000
01
#2090000
0R
b0 L
11
#2100000
01
#2110000
b11 K
b10101000 U
0$
b1 L
0N
0"
11
#2120000
01
#2130000
1R
b0 L
11
#2140000
01
#2150000
b1 L
1N
1"
11
#2160000
01
#2170000
0R
b0 L
11
#2180000
01
#2190000
b100 K
b1010000 U
1$
b1 L
0N
0"
11
#2200000
01
#2210000
1R
b0 L
11
#2220000
01
#2230000
b1 L
1N
1"
11
#2240000
01
#2250000
0R
b0 L
11
#2260000
01
#2270000
b101 K
b10100000 U
0$
b1 L
0N
0"
11
#2280000
01
#2290000
1R
b0 L
11
#2300000
01
#2310000
b1 L
1N
1"
11
#2320000
01
#2330000
0R
b0 L
11
#2340000
01
#2350000
b110 K
b1000000 U
1$
b1 L
0N
0"
11
#2360000
01
#2370000
1R
b0 L
11
#2380000
01
#2390000
b1 L
1N
1"
11
#2400000
01
#2410000
0R
b0 L
11
#2420000
01
#2430000
b111 K
b10000000 U
0$
b1 L
0N
0"
11
#2440000
01
#2450000
1R
b0 L
11
#2460000
01
#2470000
b1 L
1N
1"
11
#2480000
01
#2490000
0R
b0 L
11
#2500000
01
#2510000
b100 O
b1000 K
b0 U
1$
b1 L
0N
0"
11
#2520000
01
#2530000
15
b11110000 6
b11110000 :
1%
b111 !
b111 S
0&
b0 O
1R
b0 L
b100 T
11
#2540000
01
#2550000
0%
b1 O
1N
b0 T
1"
11
#2560000
b1 O
01
b10101011 6
b10101011 :
15
#2570000
b0 !
b0 S
1&
b10 O
b1 T
11
#2580000
01
#2590000
b10101011 U
b0 K
b10 T
b10 O
11
05
#2600000
01
#2610000
b1 L
11
#2620000
01
#2630000
0R
b0 L
11
#2640000
01
#2650000
0"
b1 K
b1010110 U
b1 L
0N
11
#2660000
01
#2670000
1R
b0 L
11
#2680000
01
#2690000
1"
b1 L
1N
11
#2700000
01
#2710000
0R
b0 L
11
#2720000
01
#2730000
0"
b10 K
b10101100 U
0$
b1 L
0N
11
#2740000
01
#2750000
1R
b0 L
11
#2760000
01
#2770000
1"
b1 L
1N
11
#2780000
01
#2790000
0R
b0 L
11
#2800000
01
#2810000
0"
b11 K
b1011000 U
1$
b1 L
0N
11
#2820000
01
#2830000
1R
b0 L
11
#2840000
01
#2850000
1"
b1 L
1N
11
#2860000
01
#2870000
0R
b0 L
11
#2880000
01
#2890000
0"
b100 K
b10110000 U
0$
b1 L
0N
11
#2900000
01
#2910000
1R
b0 L
11
#2920000
01
#2930000
1"
b1 L
1N
11
#2940000
01
#2950000
0R
b0 L
11
#2960000
01
#2970000
0"
b101 K
b1100000 U
1$
b1 L
0N
11
#2980000
01
#2990000
1R
b0 L
11
#3000000
01
#3010000
1"
b1 L
1N
11
#3020000
01
#3030000
0R
b0 L
11
#3040000
01
#3050000
0"
b110 K
b11000000 U
0$
b1 L
0N
11
#3060000
01
#3070000
1R
b0 L
11
#3080000
01
#3090000
1"
b1 L
1N
11
#3100000
01
#3110000
0R
b0 L
11
#3120000
01
#3130000
0"
b111 K
b10000000 U
1$
b1 L
0N
11
#3140000
01
#3150000
1R
b0 L
11
#3160000
01
#3170000
1"
b1 L
1N
11
#3180000
01
#3190000
0R
b0 L
11
#3200000
01
#3210000
b100 O
0"
b1000 K
b0 U
b1 L
0N
11
#3220000
01
#3230000
1%
b111 !
b111 S
0&
b0 O
1R
b0 L
b100 T
11
