results/issue-example1/example1.v
module spi_master #(
    parameter MODE = 0,              // SPI Mode (0-3)
    parameter DATA_WIDTH = 16,       // Data width in bits
    parameter NUM_SLAVES = 1,        // Number of slave devices
    parameter SLAVE_ACTIVE_LOW = 1,  // Slave select active level
    parameter MSB_FIRST = 1          // Data transmission order
)(
    input  wire                  clk,        // System clock
    input  wire                  rst_n,      // Active low reset

    // Control interface
    input  wire                  start_tx,   // Start transmission
    input  wire                  start_rx,   // Start reception
    input  wire [DATA_WIDTH-1:0] tx_data,    // Data to transmit
    output reg  [DATA_WIDTH-1:0] rx_data,    // Received data
    output reg                   busy,       // Busy signal

    // SPI interface
    output reg                   sclk,       // SPI clock
    output reg                   mosi,       // Master out, slave in
    input  wire                  miso,       // Master in, slave out
    output reg [NUM_SLAVES-1:0]  ss_n,       // Slave select (active low)

    // Interrupt (optional)
    output reg                   irq         // Interrupt request
);

    // Local parameters
    localparam SCLK_HALF_PERIOD = 250; // Fixed half SCLK period (assumes 50MHz system clock, 100kHz SPI clock)

    // State machine states
    localparam IDLE = 3'd0;
    localparam SETUP = 3'd1;
    localparam TRANSMIT = 3'd2;
    localparam RECEIVE = 3'd3;
    localparam COMPLETE = 3'd4;

    // Registers
    reg [2:0]  state;
    reg [2:0]  next_state;
    reg [15:0] clk_counter;    // SCLK generation counter
    reg [4:0]  bit_counter;    // Bit transmission counter
    reg [DATA_WIDTH-1:0] tx_shift_reg;
    reg [DATA_WIDTH-1:0] rx_shift_reg;
    reg        sclk_gen;       // SCLK generator
    reg        last_sclk;      // Previous SCLK value for edge detection

    // Clock polarity and phase for different modes
    wire CPOL = (MODE == 2) || (MODE == 3);  // Clock polarity
    wire CPHA = (MODE == 1) || (MODE == 3);  // Clock phase

    // Slave select active level
    wire SS_ACTIVE = SLAVE_ACTIVE_LOW ? 1'b0 : 1'b1;

    // State machine
    always @(posedge clk or negedge rst_n) begin
        if (!rst_n) begin
            state <= IDLE;
            clk_counter <= 0;
            bit_counter <= 0;
            tx_shift_reg <= 0;
            rx_shift_reg <= 0;
            sclk <= CPOL;  // Set initial SCLK state based on CPOL
            mosi <= 0;
            ss_n <= {NUM_SLAVES{1'b1}};
            busy <= 0;
            irq <= 0;
            last_sclk <= CPOL;
        end else begin
            state <= next_state;
            last_sclk <= sclk_gen;

            // SCLK generation
            if (state == TRANSMIT || state == RECEIVE) begin
                if (clk_counter >= SCLK_HALF_PERIOD - 1) begin
                    clk_counter <= 0;
                    sclk_gen <= ~sclk_gen;
                end else begin
                    clk_counter <= clk_counter + 1;
                end
            end else begin
                clk_counter <= 0;
                sclk_gen <= CPOL;
            end

            // Data transmission and reception
            if (state == TRANSMIT || state == RECEIVE) begin
                // Sample data on appropriate edge
                if (CPHA == 0) begin
                    // Sample on leading edge
                    if (sclk_gen != last_sclk && sclk_gen == ~CPOL) begin
                        if (bit_counter < DATA_WIDTH) begin
                            // Shift in received data
                            if (MSB_FIRST) begin
                                rx_shift_reg <= {rx_shift_reg[DATA_WIDTH-2:0], miso};
                            end else begin
                                rx_shift_reg <= {miso, rx_shift_reg[DATA_WIDTH-1:1]};
                            end

                            // Shift out transmitted data
                            if (MSB_FIRST) begin
                                mosi <= tx_shift_reg[DATA_WIDTH-1];
                                tx_shift_reg <= {tx_shift_reg[DATA_WIDTH-2:0], 1'b0};
                            end else begin
                                mosi <= tx_shift_reg[0];
                                tx_shift_reg <= {1'b0, tx_shift_reg[DATA_WIDTH-1:1]};
                            end

                            bit_counter <= bit_counter + 1;
                        end
                    end
                end else begin
                    // Sample on trailing edge
                    if (sclk_gen != last_sclk && sclk_gen == CPOL) begin
                        if (bit_counter < DATA_WIDTH) begin
                            // Shift in received data
                            if (MSB_FIRST) begin
                                rx_shift_reg <= {rx_shift_reg[DATA_WIDTH-2:0], miso};
                            end else begin
                                rx_shift_reg <= {miso, rx_shift_reg[DATA_WIDTH-1:1]};
                            end

                            // Shift out transmitted data
                            if (MSB_FIRST) begin
                                mosi <= tx_shift_reg[DATA_WIDTH-1];
                                tx_shift_reg <= {tx_shift_reg[DATA_WIDTH-2:0], 1'b0};
                            end else begin
                                mosi <= tx_shift_reg[0];
                                tx_shift_reg <= {1'b0, tx_shift_reg[DATA_WIDTH-1:1]};
                            end

                            bit_counter <= bit_counter + 1;
                        end
                    end
                end
            end
        end
    end

    // SCLK output assignment
    always @(posedge clk) begin
        sclk <= sclk_gen;
    end

    // Next state logic
    always @(*) begin
        next_state = state;

        case (state)
            IDLE: begin
                busy = 0;
                irq = 0;
                ss_n = {NUM_SLAVES{1'b1}};
                rx_data = 0;

                if (start_tx) begin
                    next_state = SETUP;
                end else if (start_rx) begin
                    next_state = SETUP;
                end
            end

            SETUP: begin
                busy = 1;
                ss_n = {NUM_SLAVES{SS_ACTIVE}};  // Activate slave select
                bit_counter = 0;
                tx_shift_reg = tx_data;
                rx_shift_reg = 0;
                next_state = TRANSMIT;
            end

            TRANSMIT: begin
                busy = 1;
                if (bit_counter >= DATA_WIDTH) begin
                    next_state = COMPLETE;
                end
            end

            RECEIVE: begin
                busy = 1;
                if (bit_counter >= DATA_WIDTH) begin
                    rx_data = rx_shift_reg;
                    next_state = COMPLETE;
                end
            end

            COMPLETE: begin
                busy = 0;
                ss_n = {NUM_SLAVES{1'b1}};  // Deactivate slave select
                irq = 1;  // Generate interrupt
                next_state = IDLE;
            end

            default: next_state = IDLE;
        endcase
    end

endmodule

results/issue-example1/example1_tb.v

`timescale 1ns / 1ps

module spi_master_tb;

    // Parameters
    parameter MODE = 0;
    parameter DATA_WIDTH = 16;
    parameter NUM_SLAVES = 1;

    // Signals
    reg clk;
    reg rst_n;
    reg start_tx;
    reg start_rx;
    reg [DATA_WIDTH-1:0] tx_data;
    wire [DATA_WIDTH-1:0] rx_data;
    wire busy;
    wire sclk;
    wire mosi;
    reg miso;
    wire [NUM_SLAVES-1:0] ss_n;
    wire irq;

    // DUT instantiation
    spi_master #(
        .MODE(MODE),
        .DATA_WIDTH(DATA_WIDTH),
        .NUM_SLAVES(NUM_SLAVES)
    ) dut (
        .clk(clk),
        .rst_n(rst_n),
        .start_tx(start_tx),
        .start_rx(start_rx),
        .tx_data(tx_data),
        .rx_data(rx_data),
        .busy(busy),
        .sclk(sclk),
        .mosi(mosi),
        .miso(miso),
        .ss_n(ss_n),
        .irq(irq)
    );

    // Clock generation
    initial begin
        clk = 0;
        forever #10 clk = ~clk;  // 50MHz clock
    end

    // Enhanced test sequence with multiple transactions
    initial begin
        // Initialize
        rst_n = 0;
        start_tx = 0;
        start_rx = 0;
        tx_data = 0;
        miso = 0;

        #100;
        rst_n = 1;
        #200;  // Allow system to stabilize

        $display("=== SPI RTL Testbench Starting ===");
        $display("Configuration: Mode 0, 16-bit data, 1 slaves");

        // Test comprehensive SPI transactions
        

        $display("--- Testing Slave 0 ---");

        // Test 1: Basic data transmission (16-bit pattern)
        tx_data = 16'hAA55;
        $display("TX Data: 0x%h", tx_data);
        start_tx = 1;
        #50;
        start_tx = 0;

        wait (!busy);
        $display("✓ Transmission complete for slave 0");

        // Small delay between transactions
        #1000;

        // Test 2: Different data pattern (alternating bits)
        tx_data = 16'hCCCC;
        $display("TX Data: 0x%h", tx_data);
        start_tx = 1;
        #50;
        start_tx = 0;

        wait (!busy);
        $display("✓ Second transmission complete for slave 0");

        

        // Test reception from all slaves
        $display("--- Testing Reception ---");

        
        // Prepare to receive data from slave 0
        start_rx = 1;
        #50;
        start_rx = 0;

        // Simulate slave providing response data
        #200;
        // Slave 0 responds with pattern: 0x55AA0
        miso = 1'b0;  // Data bit based on CPHA
        #100;
        miso = 1'b1;

        wait (!busy);
        $display("✓ Reception complete from slave 0");

        

        // Test 3: Burst transmission (multiple frames)
        $display("--- Testing Burst Transmission ---");
        
        tx_data = 16'h0000;
        $display("Burst TX[%d]: 0x%h", 0, tx_data);
        start_tx = 1;
        #30;
        start_tx = 0;

        wait (!busy);
        $display("✓ Burst transmission 0 complete");
        #500;  // Inter-frame delay
        
        tx_data = 16'h1111;
        $display("Burst TX[%d]: 0x%h", 1, tx_data);
        start_tx = 1;
        #30;
        start_tx = 0;

        wait (!busy);
        $display("✓ Burst transmission 1 complete");
        #500;  // Inter-frame delay
        
        tx_data = 16'h2222;
        $display("Burst TX[%d]: 0x%h", 2, tx_data);
        start_tx = 1;
        #30;
        start_tx = 0;

        wait (!busy);
        $display("✓ Burst transmission 2 complete");
        #500;  // Inter-frame delay
        

        // Test 4: Continuous read operations
        $display("--- Testing Continuous Read Operations ---");
        
        $display("Reading from slave 0...");

        // Simulate multiple read operations
        
        start_rx = 1;
        #40;
        start_rx = 0;

        // Simulate slave response with incrementing data
        #150;
        miso = 1'b1;

        wait (!busy);
        $display("✓ Read operation 0 from slave 0 complete");
        #300;
        
        start_rx = 1;
        #40;
        start_rx = 0;

        // Simulate slave response with incrementing data
        #150;
        miso = 1'b0;

        wait (!busy);
        $display("✓ Read operation 1 from slave 0 complete");
        #300;
        
        

        // Test 5: Mixed read/write operations
        $display("--- Testing Mixed Read/Write Operations ---");

        // Write configuration data
        tx_data = 16'h1234;
        $display("Writing config: 0x%h", tx_data);
        start_tx = 1;
        #50;
        start_tx = 0;
        wait (!busy);
        $display("✓ Configuration write complete");

        #1000;

        // Read back configuration
        $display("Reading back configuration...");
        start_rx = 1;
        #50;
        start_rx = 0;

        #200;
        miso = 1'b1;  // Slave acknowledges
        #100;
        miso = 1'b0;

        wait (!busy);
        $display("✓ Configuration read complete");

        // Final delay before completion
        #2000;
        $display("=== All Tests Completed Successfully ===");

        $finish;
    end

    // Waveform dumping - capture all signals for comprehensive analysis
    initial begin
        $dumpfile("results/issue-example1/spi_waveform.vcd");
        $dumpvars(0, spi_master_tb);  // Dump all signals in the testbench

        // Also dump internal DUT signals for detailed analysis
        $dumpvars(1, spi_master_tb.dut.sclk);
        $dumpvars(1, spi_master_tb.dut.mosi);
        $dumpvars(1, spi_master_tb.dut.miso);
        $dumpvars(1, spi_master_tb.dut.ss_n);
        $dumpvars(1, spi_master_tb.dut.busy);
        $dumpvars(1, spi_master_tb.dut.irq);
        $dumpvars(1, spi_master_tb.dut.state);
        $dumpvars(1, spi_master_tb.dut.next_state);
        $dumpvars(1, spi_master_tb.dut.bit_counter);
        $dumpvars(1, spi_master_tb.dut.clk_counter);
        $dumpvars(1, spi_master_tb.dut.tx_shift_reg);
        $dumpvars(1, spi_master_tb.dut.rx_shift_reg);
        $dumpvars(1, spi_master_tb.dut.sclk_gen);

        $dumpflush;  // Ensure all data is written
    end

endmodule

results/issue-example1/spi_waveform.vcd
$date
	Fri Sep 26 21:56:21 2025
$end
$version
	Icarus Verilog
$end
$timescale
	1ps
$end
$scope module spi_master_tb $end
$var wire 1 ! ss_n $end
$var wire 1 " sclk $end
$var wire 16 # rx_data [15:0] $end
$var wire 1 $ mosi $end
$var wire 1 % irq $end
$var wire 1 & busy $end
$var parameter 32 ' DATA_WIDTH $end
$var parameter 32 ( MODE $end
$var parameter 32 ) NUM_SLAVES $end
$var reg 1 * clk $end
$var reg 1 + miso $end
$var reg 1 , rst_n $end
$var reg 1 - start_rx $end
$var reg 1 . start_tx $end
$var reg 16 / tx_data [15:0] $end
$scope module dut $end
$var wire 1 0 CPHA $end
$var wire 1 1 CPOL $end
$var wire 1 2 SS_ACTIVE $end
$var wire 1 * clk $end
$var wire 1 + miso $end
$var wire 1 , rst_n $end
$var wire 1 - start_rx $end
$var wire 1 . start_tx $end
$var wire 16 3 tx_data [15:0] $end
$var parameter 3 4 COMPLETE $end
$var parameter 32 5 DATA_WIDTH $end
$var parameter 3 6 IDLE $end
$var parameter 32 7 MODE $end
$var parameter 32 8 MSB_FIRST $end
$var parameter 32 9 NUM_SLAVES $end
$var parameter 3 : RECEIVE $end
$var parameter 32 ; SCLK_HALF_PERIOD $end
$var parameter 3 < SETUP $end
$var parameter 32 = SLAVE_ACTIVE_LOW $end
$var parameter 3 > TRANSMIT $end
$var reg 5 ? bit_counter [4:0] $end
$var reg 1 & busy $end
$var reg 16 @ clk_counter [15:0] $end
$var reg 1 % irq $end
$var reg 1 A last_sclk $end
$var reg 1 $ mosi $end
$var reg 3 B next_state [2:0] $end
$var reg 16 C rx_data [15:0] $end
$var reg 16 D rx_shift_reg [15:0] $end
$var reg 1 " sclk $end
$var reg 1 E sclk_gen $end
$var reg 1 ! ss_n $end
$var reg 3 F state [2:0] $end
$var reg 16 G tx_shift_reg [15:0] $end
$upscope $end
$upscope $end
$enddefinitions $end
$comment Show the parameter values. $end
$dumpall
b10 >
b1 =
b1 <
b11111010 ;
b11 :
b1 9
b1 8
b0 7
b0 6
b10000 5
b100 4
b1 )
b0 (
b10000 '
$end
#0
$dumpvars
b0 G
b0 F
xE
b0 D
b0 C
b0 B
0A
b0 @
b0 ?
b0 3
02
01
00
b0 /
0.
0-
0,
0+
0*
0&
0%
0$
b0 #
0"
1!
$end
#10000
x"
1*
#20000
0*
#30000
x"
1*
#40000
0*
#50000
x"
1*
#60000
0*
#70000
x"
1*
#80000
0*
#90000
x"
1*
#100000
0*
1,
#110000
0E
xA
1*
#120000
0*
#130000
0"
0A
1*
#140000
0*
#150000
1*
#160000
0*
#170000
1*
#180000
0*
#190000
1*
#200000
0*
#210000
1*
#220000
0*
#230000
1*
#240000
0*
#250000
1*
#260000
0*
#270000
1*
#280000
0*
#290000
1*
#300000
b1 B
0*
1.
b1010101001010101 /
b1010101001010101 3
#310000
b10 B
b1010101001010101 G
0!
1&
b1 F
1*
#320000
0*
#330000
b10 F
1*
#340000
0*
#350000
b1 @
1*
0.
#360000
0*
#370000
b10 @
1*
#380000
0*
#390000
b11 @
1*
#400000
0*
#410000
b100 @
1*
#420000
0*
#430000
b101 @
1*
#440000
0*
#450000
b110 @
1*
#460000
0*
#470000
b111 @
1*
#480000
0*
#490000
b1000 @
1*
#500000
0*
#510000
b1001 @
1*
#520000
0*
#530000
b1010 @
1*
#540000
0*
#550000
b1011 @
1*
#560000
0*
#570000
b1100 @
1*
#580000
0*
#590000
b1101 @
1*
#600000
0*
#610000
b1110 @
1*
#620000
0*
#630000
b1111 @
1*
#640000
0*
#650000
b10000 @
1*
#660000
0*
#670000
b10001 @
1*
#680000
0*
#690000
b10010 @
1*
#700000
0*
#710000
b10011 @
1*
#720000
0*
#730000
b10100 @
1*
#740000
0*
#750000
b10101 @
1*
#760000
0*
#770000
b10110 @
1*
#780000
0*
#790000
b10111 @
1*
#800000
0*
#810000
b11000 @
1*
#820000
0*
#830000
b11001 @
1*
#840000
0*
#850000
b11010 @
1*
#860000
0*
#870000
b11011 @
1*
#880000
0*
#890000
b11100 @
1*
#900000
0*
#910000
b11101 @
1*
#920000
0*
#930000
b11110 @
1*
#940000
0*
#950000
b11111 @
1*
#960000
0*
#970000
b100000 @
1*
#980000
0*
#990000
b100001 @
1*
#1000000
0*
#1010000
b100010 @
1*
#1020000
0*
#1030000
b100011 @
1*
#1040000
0*
#1050000
b100100 @
1*
#1060000
0*
#1070000
b100101 @
1*
#1080000
0*
#1090000
b100110 @
1*
#1100000
0*
#1110000
b100111 @
1*
#1120000
0*
#1130000
b101000 @
1*
#1140000
0*
#1150000
b101001 @
1*
#1160000
0*
#1170000
b101010 @
1*
#1180000
0*
#1190000
b101011 @
1*
#1200000
0*
#1210000
b101100 @
1*
#1220000
0*
#1230000
b101101 @
1*
#1240000
0*
#1250000
b101110 @
1*
#1260000
0*
#1270000
b101111 @
1*
#1280000
0*
#1290000
b110000 @
1*
#1300000
0*
#1310000
b110001 @
1*
#1320000
0*
#1330000
b110010 @
1*
#1340000
0*
#1350000
b110011 @
1*
#1360000
0*
#1370000
b110100 @
1*
#1380000
0*
#1390000
b110101 @
1*
#1400000
0*
#1410000
b110110 @
1*
#1420000
0*
#1430000
b110111 @
1*
#1440000
0*
#1450000
b111000 @
1*
#1460000
0*
#1470000
b111001 @
1*
#1480000
0*
#1490000
b111010 @
1*
#1500000
0*
#1510000
b111011 @
1*
#1520000
0*
#1530000
b111100 @
1*
#1540000
0*
#1550000
b111101 @
1*
#1560000
0*
#1570000
b111110 @
1*
#1580000
0*
#1590000
b111111 @
1*
#1600000
0*
#1610000
b1000000 @
1*
#1620000
0*
#1630000
b1000001 @
1*
#1640000
0*
#1650000
b1000010 @
1*
#1660000
0*
#1670000
b1000011 @
1*
#1680000
0*
#1690000
b1000100 @
1*
#1700000
0*
#1710000
b1000101 @
1*
#1720000
0*
#1730000
b1000110 @
1*
#1740000
0*
#1750000
b1000111 @
1*
#1760000
0*
#1770000
b1001000 @
1*
#1780000
0*
#1790000
b1001001 @
1*
#1800000
0*
#1810000
b1001010 @
1*
#1820000
0*
#1830000
b1001011 @
1*
#1840000
0*
#1850000
b1001100 @
1*
#1860000
0*
#1870000
b1001101 @
1*
#1880000
0*
#1890000
b1001110 @
1*
#1900000
0*
#1910000
b1001111 @
1*
#1920000
0*
#1930000
b1010000 @
1*
#1940000
0*
#1950000
b1010001 @
1*
#1960000
0*
#1970000
b1010010 @
1*
#1980000
0*
#1990000
b1010011 @
1*
#2000000
0*
#2010000
b1010100 @
1*
#2020000
0*
#2030000
b1010101 @
1*
#2040000
0*
#2050000
b1010110 @
1*
#2060000
0*
#2070000
b1010111 @
1*
#2080000
0*
#2090000
b1011000 @
1*
#2100000
0*
#2110000
b1011001 @
1*
#2120000
0*
#2130000
b1011010 @
1*
#2140000
0*
#2150000
b1011011 @
1*
#2160000
0*
#2170000
b1011100 @
1*
#2180000
0*
#2190000
b1011101 @
1*
#2200000
0*
#2210000
b1011110 @
1*
#2220000
0*
#2230000
b1011111 @
1*
#2240000
0*
#2250000
b1100000 @
1*
#2260000
0*
#2270000
b1100001 @
1*
#2280000
0*
#2290000
b1100010 @
1*
#2300000
0*
#2310000
b1100011 @
1*
#2320000
0*
#2330000
b1100100 @
1*
#2340000
0*
#2350000
b1100101 @
1*
#2360000
0*
#2370000
b1100110 @
1*
#2380000
0*
#2390000
b1100111 @
1*
#2400000
0*
#2410000
b1101000 @
1*
#2420000
0*
#2430000
b1101001 @
1*
#2440000
0*
#2450000
b1101010 @
1*
#2460000
0*
#2470000
b1101011 @
1*
#2480000
0*
#2490000
b1101100 @
1*
#2500000
0*
#2510000
b1101101 @
1*
#2520000
0*
#2530000
b1101110 @
1*
#2540000
0*
#2550000
b1101111 @
1*
#2560000
0*
#2570000
b1110000 @
1*
#2580000
0*
#2590000
b1110001 @
1*
#2600000
0*
#2610000
b1110010 @
1*
#2620000
0*
#2630000
b1110011 @
1*
#2640000
0*
#2650000
b1110100 @
1*
#2660000
0*
#2670000
b1110101 @
1*
#2680000
0*
#2690000
b1110110 @
1*
#2700000
0*
#2710000
b1110111 @
1*
#2720000
0*
#2730000
b1111000 @
1*
#2740000
0*
#2750000
b1111001 @
1*
#2760000
0*
#2770000
b1111010 @
1*
#2780000
0*
#2790000
b1111011 @
1*
#2800000
0*
#2810000
b1111100 @
1*
#2820000
0*
#2830000
b1111101 @
1*
#2840000
0*
#2850000
b1111110 @
1*
#2860000
0*
#2870000
b1111111 @
1*
#2880000
0*
#2890000
b10000000 @
1*
#2900000
0*
#2910000
b10000001 @
1*
#2920000
0*
#2930000
b10000010 @
1*
#2940000
0*
#2950000
b10000011 @
1*
#2960000
0*
#2970000
b10000100 @
1*
#2980000
0*
#2990000
b10000101 @
1*
#3000000
0*
#3010000
b10000110 @
1*
#3020000
0*
#3030000
b10000111 @
1*
#3040000
0*
#3050000
b10001000 @
1*
#3060000
0*
#3070000
b10001001 @
1*
#3080000
0*
#3090000
b10001010 @
1*
#3100000
0*
#3110000
b10001011 @
1*
#3120000
0*
#3130000
b10001100 @
1*
#3140000
0*
#3150000
b10001101 @
1*
#3160000
0*
#3170000
b10001110 @
1*
#3180000
0*
#3190000
b10001111 @
1*
#3200000
0*
#3210000
b10010000 @
1*
#3220000
0*
#3230000
b10010001 @
1*
#3240000
0*
#3250000
b10010010 @
1*
#3260000
0*
#3270000
b10010011 @
1*
#3280000
0*
#3290000
b10010100 @
1*
#3300000
0*
#3310000
b10010101 @
1*
#3320000
0*
#3330000
b10010110 @
1*
#3340000
0*
#3350000
b10010111 @
1*
#3360000
0*
#3370000
b10011000 @
1*
#3380000
0*
#3390000
b10011001 @
1*
#3400000
0*
#3410000
b10011010 @
1*
#3420000
0*
#3430000
b10011011 @
1*
#3440000
0*
#3450000
b10011100 @
1*
#3460000
0*
#3470000
b10011101 @
1*
#3480000
0*
#3490000
b10011110 @
1*
#3500000
0*
#3510000
b10011111 @
1*
#3520000
0*
#3530000
b10100000 @
1*
#3540000
0*
#3550000
b10100001 @
1*
#3560000
0*
#3570000
b10100010 @
1*
#3580000
0*
#3590000
b10100011 @
1*
#3600000
0*
#3610000
b10100100 @
1*
#3620000
0*
#3630000
b10100101 @
1*
#3640000
0*
#3650000
b10100110 @
1*
#3660000
0*
#3670000
b10100111 @
1*
#3680000
0*
#3690000
b10101000 @
1*
#3700000
0*
#3710000
b10101001 @
1*
#3720000
0*
#3730000
b10101010 @
1*
#3740000
0*
#3750000
b10101011 @
1*
#3760000
0*
#3770000
b10101100 @
1*
#3780000
0*
#3790000
b10101101 @
1*
#3800000
0*
#3810000
b10101110 @
1*
#3820000
0*
#3830000
b10101111 @
1*
#3840000
0*
#3850000
b10110000 @
1*
#3860000
0*
#3870000
b10110001 @
1*
#3880000
0*
#3890000
b10110010 @
1*
#3900000
0*
#3910000
b10110011 @
1*
#3920000
0*
#3930000
b10110100 @
1*
#3940000
0*
#3950000
b10110101 @
1*
#3960000
0*
#3970000
b10110110 @
1*
#3980000
0*
#3990000
b10110111 @
1*
#4000000
0*
#4010000
b10111000 @
1*
#4020000
0*
#4030000
b10111001 @
1*
#4040000
0*
#4050000
b10111010 @
1*
#4060000
0*
#4070000
b10111011 @
1*
#4080000
0*
#4090000
b10111100 @
1*
#4100000
0*
#4110000
b10111101 @
1*
#4120000
0*
#4130000
b10111110 @
1*
#4140000
0*
#4150000
b10111111 @
1*
#4160000
0*
#4170000
b11000000 @
1*
#4180000
0*
#4190000
b11000001 @
1*
#4200000
0*
#4210000
b11000010 @
1*
#4220000
0*
#4230000
b11000011 @
1*
#4240000
0*
#4250000
b11000100 @
1*
#4260000
0*
#4270000
b11000101 @
1*
#4280000
0*
#4290000
b11000110 @
1*
#4300000
0*
#4310000
b11000111 @
1*
#4320000
0*
#4330000
b11001000 @
1*
#4340000
0*
#4350000
b11001001 @
1*
#4360000
0*
#4370000
b11001010 @
1*
#4380000
0*
#4390000
b11001011 @
1*
#4400000
0*
#4410000
b11001100 @
1*
#4420000
0*
#4430000
b11001101 @
1*
#4440000
0*
#4450000
b11001110 @
1*
#4460000
0*
#4470000
b11001111 @
1*
#4480000
0*
#4490000
b11010000 @
1*
#4500000
0*
#4510000
b11010001 @
1*
#4520000
0*
#4530000
b11010010 @
1*
#4540000
0*
#4550000
b11010011 @
1*
#4560000
0*
#4570000
b11010100 @
1*
#4580000
0*
#4590000
b11010101 @
1*
#4600000
0*
#4610000
b11010110 @
1*
#4620000
0*
#4630000
b11010111 @
1*
#4640000
0*
#4650000
b11011000 @
1*
#4660000
0*
#4670000
b11011001 @
1*
#4680000
0*
#4690000
b11011010 @
1*
#4700000
0*
#4710000
b11011011 @
1*
#4720000
0*
#4730000
b11011100 @
1*
#4740000
0*
#4750000
b11011101 @
1*
#4760000
0*
#4770000
b11011110 @
1*
#4780000
0*
#4790000
b11011111 @
1*
#4800000
0*
#4810000
b11100000 @
1*
#4820000
0*
#4830000
b11100001 @
1*
#4840000
0*
#4850000
b11100010 @
1*
#4860000
0*
#4870000
b11100011 @
1*
#4880000
0*
#4890000
b11100100 @
1*
#4900000
0*
#4910000
b11100101 @
1*
#4920000
0*
#4930000
b11100110 @
1*
#4940000
0*
#4950000
b11100111 @
1*
#4960000
0*
#4970000
b11101000 @
1*
#4980000
0*
#4990000
b11101001 @
1*
#5000000
0*
#5010000
b11101010 @
1*
#5020000
0*
#5030000
b11101011 @
1*
#5040000
0*
#5050000
b11101100 @
1*
#5060000
0*
#5070000
b11101101 @
1*
#5080000
0*
#5090000
b11101110 @
1*
#5100000
0*
#5110000
b11101111 @
1*
#5120000
0*
#5130000
b11110000 @
1*
#5140000
0*
#5150000
b11110001 @
1*
#5160000
0*
#5170000
b11110010 @
1*
#5180000
0*
#5190000
b11110011 @
1*
#5200000
0*
#5210000
b11110100 @
1*
#5220000
0*
#5230000
b11110101 @
1*
#5240000
0*
#5250000
b11110110 @
1*
#5260000
0*
#5270000
b11110111 @
1*
#5280000
0*
#5290000
b11111000 @
1*
#5300000
0*
#5310000
b11111001 @
1*
#5320000
0*
#5330000
1E
b0 @
1*
#5340000
0*
#5350000
1"
b1 ?
b101010010101010 G
1$
b1 @
1A
1*
#5360000
0*
#5370000
b10 @
1*
#5380000
0*
#5390000
b11 @
1*
#5400000
0*
#5410000
b100 @
1*
#5420000
0*
#5430000
b101 @
1*
#5440000
0*
#5450000
b110 @
1*
#5460000
0*
#5470000
b111 @
1*
#5480000
0*
#5490000
b1000 @
1*
#5500000
0*
#5510000
b1001 @
1*
#5520000
0*
#5530000
b1010 @
1*
#5540000
0*
#5550000
b1011 @
1*
#5560000
0*
#5570000
b1100 @
1*
#5580000
0*
#5590000
b1101 @
1*
#5600000
0*
#5610000
b1110 @
1*
#5620000
0*
#5630000
b1111 @
1*
#5640000
0*
#5650000
b10000 @
1*
#5660000
0*
#5670000
b10001 @
1*
#5680000
0*
#5690000
b10010 @
1*
#5700000
0*
#5710000
b10011 @
1*
#5720000
0*
#5730000
b10100 @
1*
#5740000
0*
#5750000
b10101 @
1*
#5760000
0*
#5770000
b10110 @
1*
#5780000
0*
#5790000
b10111 @
1*
#5800000
0*
#5810000
b11000 @
1*
#5820000
0*
#5830000
b11001 @
1*
#5840000
0*
#5850000
b11010 @
1*
#5860000
0*
#5870000
b11011 @
1*
#5880000
0*
#5890000
b11100 @
1*
#5900000
0*
#5910000
b11101 @
1*
#5920000
0*
#5930000
b11110 @
1*
#5940000
0*
#5950000
b11111 @
1*
#5960000
0*
#5970000
b100000 @
1*
#5980000
0*
#5990000
b100001 @
1*
#6000000
0*
#6010000
b100010 @
1*
#6020000
0*
#6030000
b100011 @
1*
#6040000
0*
#6050000
b100100 @
1*
#6060000
0*
#6070000
b100101 @
1*
#6080000
0*
#6090000
b100110 @
1*
#6100000
0*
#6110000
b100111 @
1*
#6120000
0*
#6130000
b101000 @
1*
#6140000
0*
#6150000
b101001 @
1*
#6160000
0*
#6170000
b101010 @
1*
#6180000
0*
#6190000
b101011 @
1*
#6200000
0*
#6210000
b101100 @
1*
#6220000
0*
#6230000
b101101 @
1*
#6240000
0*
#6250000
b101110 @
1*
#6260000
0*
#6270000
b101111 @
1*
#6280000
0*
#6290000
b110000 @
1*
#6300000
0*
#6310000
b110001 @
1*
#6320000
0*
#6330000
b110010 @
1*
#6340000
0*
#6350000
b110011 @
1*
#6360000
0*
#6370000
b110100 @
1*
#6380000
0*
#6390000
b110101 @
1*
#6400000
0*
#6410000
b110110 @
1*
#6420000
0*
#6430000
b110111 @
1*
#6440000
0*
#6450000
b111000 @
1*
#6460000
0*
#6470000
b111001 @
1*
#6480000
0*
#6490000
b111010 @
1*
#6500000
0*
#6510000
b111011 @
1*
#6520000
0*
#6530000
b111100 @
1*
#6540000
0*
#6550000
b111101 @
1*
#6560000
0*
#6570000
b111110 @
1*
#6580000
0*
#6590000
b111111 @
1*
#6600000
0*
#6610000
b1000000 @
1*
#6620000
0*
#6630000
b1000001 @
1*
#6640000
0*
#6650000
b1000010 @
1*
#6660000
0*
#6670000
b1000011 @
1*
#6680000
0*
#6690000
b1000100 @
1*
#6700000
0*
#6710000
b1000101 @
1*
#6720000
0*
#6730000
b1000110 @
1*
#6740000
0*
#6750000
b1000111 @
1*
#6760000
0*
#6770000
b1001000 @
1*
#6780000
0*
#6790000
b1001001 @
1*
#6800000
0*
#6810000
b1001010 @
1*
#6820000
0*
#6830000
b1001011 @
1*
#6840000
0*
#6850000
b1001100 @
1*
#6860000
0*
#6870000
b1001101 @
1*
#6880000
0*
#6890000
b1001110 @
1*
#6900000
0*
#6910000
b1001111 @
1*
#6920000
0*
#6930000
b1010000 @
1*
#6940000
0*
#6950000
b1010001 @
1*
#6960000
0*
#6970000
b1010010 @
1*
#6980000
0*
#6990000
b1010011 @
1*
#7000000
0*
#7010000
b1010100 @
1*
#7020000
0*
#7030000
b1010101 @
1*
#7040000
0*
#7050000
b1010110 @
1*
#7060000
0*
#7070000
b1010111 @
1*
#7080000
0*
#7090000
b1011000 @
1*
#7100000
0*
#7110000
b1011001 @
1*
#7120000
0*
#7130000
b1011010 @
1*
#7140000
0*
#7150000
b1011011 @
1*
#7160000
0*
#7170000
b1011100 @
1*
#7180000
0*
#7190000
b1011101 @
1*
#7200000
0*
#7210000
b1011110 @
1*
#7220000
0*
#7230000
b1011111 @
1*
#7240000
0*
#7250000
b1100000 @
1*
#7260000
0*
#7270000
b1100001 @
1*
#7280000
0*
#7290000
b1100010 @
1*
#7300000
0*
#7310000
b1100011 @
1*
#7320000
0*
#7330000
b1100100 @
1*
#7340000
0*
#7350000
b1100101 @
1*
#7360000
0*
#7370000
b1100110 @
1*
#7380000
0*
#7390000
b1100111 @
1*
#7400000
0*
#7410000
b1101000 @
1*
#7420000
0*
#7430000
b1101001 @
1*
#7440000
0*
#7450000
b1101010 @
1*
#7460000
0*
#7470000
b1101011 @
1*
#7480000
0*
#7490000
b1101100 @
1*
#7500000
0*
#7510000
b1101101 @
1*
#7520000
0*
#7530000
b1101110 @
1*
#7540000
0*
#7550000
b1101111 @
1*
#7560000
0*
#7570000
b1110000 @
1*
#7580000
0*
#7590000
b1110001 @
1*
