results/issue-56/code/spi_slave_mode0_1bit.v
// =============================================
// SPI Slave Core - Auto-generated by SPI Customizer
// =============================================

module spi_slave #(
    parameter MODE = 0,                    // SPI mode (0, 1, 2, 3)
    parameter DATA_WIDTH = 1,        // Data width in bits
    parameter SLAVE_ACTIVE_LOW = 1,  // Slave select polarity
    parameter MSB_FIRST = 0,  // Data order
    parameter FIFO_DEPTH = 16,        // FIFO buffer depth
    parameter MAX_SLAVES = 8,        // Maximum slaves supported
    parameter DEFAULT_DATA_ENABLED = 0,
    parameter DEFAULT_DATA_PATTERN = "ffff",
    parameter DEFAULT_DATA_VALUE = 1'hF
)(
    // System signals
    input  wire clk,                    // System clock
    input  wire rst_n,                  // Active-low reset

    // SPI Slave Interface
    input  wire sclk,                   // SPI clock from master
    input  wire mosi,                   // Master Out Slave In
    output wire miso,                   // Master In Slave Out
    input  wire ss_n,                   // Slave Select (active low)

    // Data interface
    output wire [DATA_WIDTH-1:0] rx_data,  // Received data
    input  wire [DATA_WIDTH-1:0] tx_data,  // Data to transmit
    output wire rx_valid,               // Receive data valid
    output wire tx_ready,               // Ready to accept new transmit data
    input  wire tx_valid,               // Transmit data valid

    // Control and status
    output wire busy,                   // SPI transaction in progress
    output wire irq,                    // Interrupt request
    input  wire irq_clear               // Clear interrupt
);

// =============================================
// Local Parameters
// =============================================
localparam FIFO_WIDTH = $clog2(FIFO_DEPTH);
localparam SLAVE_ID = 0;  // Default slave ID

// Mode parameters
localparam CPOL = (MODE >> 1);  // Clock polarity
localparam CPHA = (MODE & 1);   // Clock phase
localparam SAMPLE_ON_RISING = (MODE == 0 || MODE == 3);
localparam SS_ACTIVE_LEVEL = SLAVE_ACTIVE_LOW ? 1'b0 : 1'b1;
localparam SS_INACTIVE_LEVEL = ~SS_ACTIVE_LEVEL;

// =============================================
// Internal Signals
// =============================================

// Clock domain signals
reg [15:0] bit_counter;
reg [2:0] state, next_state;
reg [DATA_WIDTH-1:0] shift_reg_rx;
reg [DATA_WIDTH-1:0] shift_reg_tx;
reg [DATA_WIDTH-1:0] rx_data_reg;
reg miso_reg;

// Control signals
reg ss_n_sync, ss_n_prev;
reg sclk_sync, sclk_prev;
wire sample_edge, shift_edge;
wire ss_selected, ss_released;

// FIFO signals
reg fifo_wr_en;
reg [DATA_WIDTH-1:0] fifo_wr_data;
wire fifo_full, fifo_empty;
wire [DATA_WIDTH-1:0] fifo_rd_data;

// Interrupt and status
reg irq_reg;
reg busy_reg;

// Default data generation
reg [DATA_WIDTH-1:0] default_data;

// =============================================
// State Machine Definition
// =============================================
localparam IDLE    = 3'b000;
localparam RECEIVE = 3'b001;
localparam TRANSMIT = 3'b010;
localparam COMPLETE = 3'b011;
localparam ERROR   = 3'b100;

// =============================================
// Default Data Pattern Generator
// =============================================
always @(posedge clk or negedge rst_n) begin
    if (!rst_n) begin
        default_data <= DEFAULT_DATA_VALUE;
    end else if (DEFAULT_DATA_ENABLED) begin
        case (DEFAULT_DATA_PATTERN)
            "a5a5": default_data <= 1'hA5A5;
            "ffff": default_data <= 1'hFFFF;
            "0000": default_data <= 1'h0000;
            "5555": default_data <= 1'h5555;
            default: default_data <= DEFAULT_DATA_VALUE;
        endcase
    end
end

// =============================================
// Synchronization Registers
// =============================================
always @(posedge clk or negedge rst_n) begin
    if (!rst_n) begin
        ss_n_sync <= SS_INACTIVE_LEVEL;
        ss_n_prev <= SS_INACTIVE_LEVEL;
        sclk_sync <= 1'b0;
        sclk_prev <= 1'b0;
    end else begin
        ss_n_sync <= ss_n;
        ss_n_prev <= ss_n_sync;
        sclk_sync <= sclk;
        sclk_prev <= sclk_sync;
    end
end

// =============================================
// Edge Detection (combinational from synchronized clock)
// =============================================
assign sample_edge = SAMPLE_ON_RISING ? (~sclk_prev & sclk_sync) : (sclk_prev & ~sclk_sync);
assign shift_edge = SAMPLE_ON_RISING ? (sclk_prev & ~sclk_sync) : (~sclk_prev & sclk_sync);
assign ss_selected = (ss_n == SS_ACTIVE_LEVEL);
assign ss_released = (ss_n == SS_INACTIVE_LEVEL);

// =============================================
// Main State Machine
// =============================================
always @(posedge clk or negedge rst_n) begin
    if (!rst_n) begin
        state <= IDLE;
        bit_counter <= 16'd0;
        shift_reg_rx <= {DATA_WIDTH{1'b0}};
        shift_reg_tx <= {DATA_WIDTH{1'b0}};
        rx_data_reg <= {DATA_WIDTH{1'b0}};
        miso_reg <= 1'b0;
        busy_reg <= 1'b0;
        irq_reg <= 1'b0;
    end else begin
        state <= next_state;

        case (state)
            IDLE: begin
                bit_counter <= 16'd0;
                busy_reg <= 1'b0;
                if (ss_selected) begin  // Slave selected
                    busy_reg <= 1'b1;
                    shift_reg_tx <= tx_valid ? tx_data : default_data;
                end
            end

            RECEIVE: begin
                if (sample_edge && bit_counter < DATA_WIDTH) begin
                    if (MSB_FIRST) begin
                        shift_reg_rx[DATA_WIDTH - 1 - bit_counter] <= mosi;
                    end else begin
                        shift_reg_rx[bit_counter] <= mosi;
                    end
                    bit_counter <= bit_counter + 1'b1;
                end
            end

            TRANSMIT: begin
                if (shift_edge) begin
                    if (MSB_FIRST) begin
                        miso_reg <= shift_reg_tx[DATA_WIDTH-1];
                        if (DATA_WIDTH > 1) begin
                            shift_reg_tx <= {shift_reg_tx[DATA_WIDTH-2:0], 1'b0};
                        end else begin
                            shift_reg_tx <= 1'b0;
                        end
                    end else begin
                        miso_reg <= shift_reg_tx[0];
                        if (DATA_WIDTH > 1) begin
                            shift_reg_tx <= {1'b0, shift_reg_tx[DATA_WIDTH-1:1]};
                        end else begin
                            shift_reg_tx <= 1'b0;
                        end
                    end
                    bit_counter <= bit_counter + 1'b1;
                end
            end

            COMPLETE: begin
                rx_data_reg <= shift_reg_rx;
                irq_reg <= 1'b1;
            end

            ERROR: begin
                // Handle error condition
                bit_counter <= 16'd0;
            end
        endcase
    end
end

// =============================================
// Next State Logic
// =============================================
always @(*) begin
    next_state = state;

    case (state)
        IDLE: begin
            if (ss_selected) begin  // Slave selected
                next_state = RECEIVE;
            end
        end

        RECEIVE: begin
            if (bit_counter >= DATA_WIDTH) begin
                next_state = COMPLETE;
            end
        end

        COMPLETE: begin
            if (ss_released) begin  // Slave deselected
                next_state = IDLE;
            end
        end

        default: next_state = IDLE;
    endcase
end

// =============================================
// Output Assignments
// =============================================
assign rx_data = rx_data_reg;
assign rx_valid = (state == COMPLETE) || ((ss_n_sync == SS_INACTIVE_LEVEL) && (bit_counter >= DATA_WIDTH));
assign tx_ready = (state == IDLE);
assign miso = miso_reg;
assign busy = busy_reg;
assign irq = irq_reg & ~irq_clear;

// =============================================
// FIFO Implementation (if enabled)
// =============================================


// =============================================
// Debug Signals (for testing)
// =============================================
wire [2:0] debug_state = state;
wire [15:0] debug_bit_count = bit_counter;

endmodule

results/issue-56/code/spi_slave_tb.v
// =============================================
// SPI Slave Testbench - Auto-generated by SPI Customizer
// =============================================

`timescale 1ns / 1ps

module spi_slave_tb;

    // Parameters
    parameter MODE = 0;
    parameter DATA_WIDTH = 1;
    parameter NUM_SLAVES = 3;
    parameter SLAVE_ACTIVE_LOW = 1;
    parameter MSB_FIRST = 0;
    parameter FIFO_DEPTH = 16;
    parameter MAX_SLAVES = 8;
    parameter DEFAULT_DATA_ENABLED = 0;
    parameter DEFAULT_DATA_PATTERN = "ffff";
    parameter DEFAULT_DATA_VALUE = 1'hF;
    localparam SS_ACTIVE = SLAVE_ACTIVE_LOW ? 1'b0 : 1'b1;
    localparam SS_INACTIVE = ~SS_ACTIVE;

    // Signals
    reg clk;
    reg rst_n;
    reg sclk_in;
    reg mosi_in;
    wire miso_out;
    reg ss_in;
    reg [DATA_WIDTH-1:0] tx_data;
    wire [DATA_WIDTH-1:0] rx_data;
    wire rx_valid;
    wire tx_ready;
    wire busy;
    wire irq;
    integer i;
    integer timeout_cycles;
    reg [DATA_WIDTH-1:0] expected_rx;
    reg rx_valid_seen;

    // DUT instantiation
    spi_slave #(
        .MODE(MODE),
        .DATA_WIDTH(DATA_WIDTH),
        .SLAVE_ACTIVE_LOW(SLAVE_ACTIVE_LOW),
        .MSB_FIRST(MSB_FIRST),
        .FIFO_DEPTH(FIFO_DEPTH),
        .MAX_SLAVES(MAX_SLAVES),
        .DEFAULT_DATA_ENABLED(DEFAULT_DATA_ENABLED),
        .DEFAULT_DATA_PATTERN(DEFAULT_DATA_PATTERN),
        .DEFAULT_DATA_VALUE(DEFAULT_DATA_VALUE)
    ) dut (
        .clk(clk),
        .rst_n(rst_n),
        .sclk(sclk_in),
        .mosi(mosi_in),
        .miso(miso_out),
        .ss_n(ss_in),
        .rx_data(rx_data),
        .tx_data(tx_data),
        .rx_valid(rx_valid),
        .tx_ready(tx_ready),
        .tx_valid(tx_ready),  // Slave uses tx_ready as tx_valid input
        .busy(busy),
        .irq(irq),
        .irq_clear(1'b0)
    );

    // Clock generation
    initial begin
        clk = 0;
        forever #10 clk = ~clk;  // 50MHz clock
    end

    // Test sequence for slave mode
    initial begin
        // Initialize
        rst_n = 0;
        sclk_in = (MODE == 2 || MODE == 3) ? 1 : 0;  // CPOL idle state
        mosi_in = 0;
        ss_in = SS_INACTIVE;  // Deactivate slave select initially
        tx_data = 0;
        expected_rx = {DATA_WIDTH{1'b0}};
        rx_valid_seen = 1'b0;

        #100;
        rst_n = 1;
        #200;  // Allow system to stabilize

        $display("=== SPI Slave RTL Testbench Starting ===");
        $display("Configuration: Mode %d, %d-bit data, Slave mode", MODE, DATA_WIDTH);

        // Act as master to test the slave with deterministic payload checks.
        $display("--- Testing Slave with Deterministic Transaction ---");
        tx_data = 1'h3C;
        expected_rx = 1'hA5;
        if (MSB_FIRST)
            mosi_in = expected_rx[DATA_WIDTH - 1];
        else
            mosi_in = expected_rx[0];

        #100;
        ss_in = SS_ACTIVE;  // Select slave
        timeout_cycles = 0;
        while (!busy && timeout_cycles < 50) begin
            #20;
            timeout_cycles = timeout_cycles + 1;
        end
        if (!busy) begin
            $fatal(1, "Slave did not assert busy after selection within timeout");
        end
        #100;  // Guard window for SS/sclk synchronization before first data bit

        for (i = 0; i < DATA_WIDTH; i = i + 1) begin
            if (MSB_FIRST)
                mosi_in = expected_rx[DATA_WIDTH - 1 - i];
            else
                mosi_in = expected_rx[i];
            #100;
            sclk_in = 1; // Leading edge
            #100;
            sclk_in = 0; // Trailing edge
            #120; // Hold MOSI after trailing edge for synchronized sample stability
        end

        #100;
        ss_in = SS_INACTIVE;  // Deselect slave
        timeout_cycles = 0;
        while (busy && timeout_cycles < 50) begin
            #20;
            timeout_cycles = timeout_cycles + 1;
        end
        if (busy) begin
            $fatal(1, "Slave busy did not clear after deselection within timeout");
        end

        timeout_cycles = 0;
        while (!rx_valid_seen && timeout_cycles < 200) begin
            #20;
            timeout_cycles = timeout_cycles + 1;
        end
        if (!rx_valid_seen) begin
            $fatal(1, "Slave rx_valid did not assert within timeout");
        end
        if (rx_data !== expected_rx) begin
            $fatal(1, "Slave RX mismatch. expected=0x%h got=0x%h", expected_rx, rx_data);
        end

        $display("=== All Slave Tests Completed Successfully ===");
        $finish;
    end

    // Latch rx_valid pulse so checks are robust to single-cycle assertion.
    always @(posedge clk or negedge rst_n) begin
        if (!rst_n)
            rx_valid_seen <= 1'b0;
        else if (rx_valid)
            rx_valid_seen <= 1'b1;
    end

    // VCD dumping
    initial begin
        $dumpfile("results/issue-56/data/spi_waveform.vcd");
        $dumpvars(0, spi_slave_tb);
    end

endmodule

results/issue-56/data/spi_waveform.vcd
$date
	Mon Apr 27 20:26:47 2026
$end
$version
	Icarus Verilog
$end
$timescale
	1ps
$end
$scope module spi_slave_tb $end
$var wire 1 ! tx_ready $end
$var wire 1 " rx_valid $end
$var wire 1 # rx_data $end
$var wire 1 $ miso_out $end
$var wire 1 % irq $end
$var wire 1 & busy $end
$var reg 1 ' clk $end
$var reg 1 ( expected_rx $end
$var reg 1 ) mosi_in $end
$var reg 1 * rst_n $end
$var reg 1 + rx_valid_seen $end
$var reg 1 , sclk_in $end
$var reg 1 - ss_in $end
$var reg 1 . tx_data $end
$var integer 32 / i [31:0] $end
$var integer 32 0 timeout_cycles [31:0] $end
$scope module dut $end
$var wire 1 & busy $end
$var wire 1 ' clk $end
$var wire 16 1 debug_bit_count [15:0] $end
$var wire 3 2 debug_state [2:0] $end
$var wire 1 % irq $end
$var wire 1 3 irq_clear $end
$var wire 1 $ miso $end
$var wire 1 ) mosi $end
$var wire 1 * rst_n $end
$var wire 1 # rx_data $end
$var wire 1 " rx_valid $end
$var wire 1 4 sample_edge $end
$var wire 1 , sclk $end
$var wire 1 5 shift_edge $end
$var wire 1 - ss_n $end
$var wire 1 6 ss_released $end
$var wire 1 7 ss_selected $end
$var wire 1 . tx_data $end
$var wire 1 ! tx_valid $end
$var wire 1 ! tx_ready $end
$var reg 16 8 bit_counter [15:0] $end
$var reg 1 9 busy_reg $end
$var reg 1 : default_data $end
$var reg 1 ; irq_reg $end
$var reg 1 < miso_reg $end
$var reg 3 = next_state [2:0] $end
$var reg 1 > rx_data_reg $end
$var reg 1 ? sclk_prev $end
$var reg 1 @ sclk_sync $end
$var reg 1 A shift_reg_rx $end
$var reg 1 B shift_reg_tx $end
$var reg 1 C ss_n_prev $end
$var reg 1 D ss_n_sync $end
$var reg 3 E state [2:0] $end
$upscope $end
$upscope $end
$enddefinitions $end
#0
$dumpvars
b0 E
1D
1C
0B
0A
0@
0?
0>
b0 =
0<
0;
1:
09
b0 8
07
16
05
04
03
b0 2
b0 1
bx 0
bx /
0.
1-
0,
0+
0*
0)
0(
0'
0&
0%
0$
0#
0"
1!
$end
#10000
1'
#20000
0'
#30000
1'
#40000
0'
#50000
1'
#60000
0'
#70000
1'
#80000
0'
#90000
1'
#100000
0'
1*
#110000
1'
#120000
0'
#130000
1'
#140000
0'
#150000
1'
#160000
0'
#170000
1'
#180000
0'
#190000
1'
#200000
0'
#210000
1'
#220000
0'
#230000
1'
#240000
0'
#250000
1'
#260000
0'
#270000
1'
#280000
0'
#290000
1'
#300000
0'
1)
1(
#310000
1'
#320000
0'
#330000
1'
#340000
0'
#350000
1'
#360000
0'
#370000
1'
#380000
0'
#390000
1'
#400000
b1 =
17
06
0'
b0 0
0-
#410000
1&
19
0!
b1 2
b1 E
0D
1'
#420000
0'
b1 0
#430000
0C
1'
#440000
0'
#450000
1'
#460000
0'
#470000
1'
#480000
0'
#490000
1'
#500000
0'
#510000
1'
#520000
0'
b0 /
#530000
1'
#540000
0'
#550000
1'
#560000
0'
#570000
1'
#580000
0'
#590000
1'
#600000
0'
#610000
1'
#620000
0'
1,
#630000
14
1@
1'
#640000
0'
#650000
04
b11 =
b1 1
b1 8
1A
1?
1'
#660000
0'
#670000
1"
b11 2
b11 E
1'
#680000
0'
#690000
1%
1+
1;
1#
1>
1'
#700000
0'
#710000
1'
#720000
0'
0,
#730000
15
0@
1'
#740000
0'
#750000
05
0?
1'
#760000
0'
#770000
1'
#780000
0'
#790000
1'
#800000
0'
#810000
1'
#820000
0'
#830000
1'
#840000
0'
b1 /
#850000
1'
#860000
0'
#870000
1'
#880000
0'
#890000
1'
#900000
0'
#910000
1'
#920000
0'
#930000
1'
#940000
b0 =
07
16
0'
b0 0
1-
#950000
1"
1D
1!
b0 2
b0 E
1'
#960000
0'
b1 0
#970000
0"
0&
09
b0 1
b0 8
1C
1'
#980000
0'
b0 0
